{"metadata": {"dataVersion": "2", "matchId": "KR_6797039172", "participants": ["SS0I_KzXcaR7hS4l5pCxl5PMsfVO2EYbcIYkEg1OHE8J3GBNL8EmeKaQUYcywvtM-qYDeUP2A2WyFw", "OqkL0mf8VRsgWZ0OKAmRzO9y3nXrvwPSR9B8o60hry_8gy2E8XJtPFo3DsDqe03u9935GisPXMauKQ", "dwu7JEPK-98Kn7XncFjtZxqQCREu1eTyH6wD4jpU4FgrLYjcqAAzWG3JsBQgLX6BUOxODN93DFQw7w", "kDQhGtqOg0LIyquTm6_dM93pBlbFT1l3t05HstPYs1Bz1-B0Hi7UF3rVBppD2JTx9JN7LSPgfAbdNw", "Vy4lRp1s28kxuawBMEC5Fdn76cvYqrHmXkc4kwsfP0i0hbJXqUfz212YN1Oat-nylR59dsgV9AJNng", "QLRveNy3l6G9GmT9i_0Z-K8iDtmADeRDiUMoJj5XaAAWpNjFD2vnyx9uecpZI0tsQUUVIfmy7iRbAg", "Aq4YLtm0owrzOJLu39GNZRkP4XolZhluorBpIc-jiFs5WI9DiH3ciys7vcMrg835hG7C4tA78wiDfQ", "XPQ59AkWr0BfSsB9vBnZKvbSahQh5Ikv7XPy_tqzsD8u03jKOY7jARIzl5pG1cyyiLh1_Wd6PAHk0g", "NHNmXsPqDG4Uvq9NX87StQTfR5oBEqb5hf-E7yx29CQZgSNpYKZuPdYh4ufzZ1nsYWTvckOUaW7KFw", "hSFj7234LwYnykejPCdj_qggqmlUtktq91j8eXzEvOAtgnM0Tx8wHskMz40Vc5KWt8zjjRlOEuJ9YQ"]}, "info": {"gameCreation": 1699963673046, "gameDuration": 1707, "gameEndTimestamp": 1699965404172, "gameId": 6797039172, "gameMode": "CLASSIC", "gameName": "teambuilder-match-6797039172", "gameStartTimestamp": 1699963696397, "gameType": "MATCHED_GAME", "gameVersion": "13.22.541.9804", "mapId": 11, "participants": [{"allInPings": 0, "assistMePings": 1, "assists": 2, "baitPings": 0, "baronKills": 0, "basicPings": 0, "bountyLevel": 12, "challenges": {"12AssistStreakCount": 0, "abilityUses": 251, "acesBefore15Minutes": 0, "alliedJungleMonsterKills": 1, "baronBuffGoldAdvantageOverThreshold": 1, "baronTakedowns": 1, "blastConeOppositeOpponentCount": 0, "bountyGold": 0, "buffsStolen": 0, "completeSupportQuestInTime": 0, "controlWardsPlaced": 0, "damagePerMinute": 948.5780017754432, "damageTakenOnTeamPercentage": 0.28512296215238464, "dancedWithRiftHerald": 0, "deathsByEnemyChamps": 0, "dodgeSkillShotsSmallWindow": 2, "doubleAces": 0, "dragonTakedowns": 1, "earliestBaron": 1532.7408173, "earliestDragonTakedown": 1421.3926979, "earlyLaningPhaseGoldExpAdvantage": 0, "effectiveHealAndShielding": 0, "elderDragonKillsWithOpposingSoul": 0, "elderDragonMultikills": 0, "enemyChampionImmobilizations": 31, "enemyJungleMonsterKills": 0, "epicMonsterKillsNearEnemyJungler": 0, "epicMonsterKillsWithin30SecondsOfSpawn": 0, "epicMonsterSteals": 0, "epicMonsterStolenWithoutSmite": 0, "fastestLegendary": 1382.3769433, "firstTurretKilled": 1, "firstTurretKilledTime": 770.0367633, "flawlessAces": 0, "fullTeamTakedown": 0, "gameLength": 1707.9645269999999, "getTakedownsInAllLanesEarlyJungleAsLaner": 0, "goldPerMinute": 547.3099251902672, "hadOpenNexus": 0, "immobilizeAndKillWithAlly": 9, "initialBuffCount": 0, "initialCrabCount": 0, "jungleCsBefore10Minutes": 0, "junglerTakedownsNearDamagedEpicMonster": 0, "kTurretsDestroyedBeforePlatesFall": 1, "kda": 14, "killAfterHiddenWithAlly": 0, "killParticipation": 0.4, "killedChampTookFullTeamDamageSurvived": 0, "killingSprees": 1, "killsNearEnemyTurret": 1, "killsOnOtherLanesEarlyJungleAsLaner": 1, "killsOnRecentlyHealedByAramPack": 0, "killsUnderOwnTurret": 0, "killsWithHelpFromEpicMonster": 0, "knockEnemyIntoTeamAndKill": 5, "landSkillShotsEarlyGame": 4, "laneMinionsFirst10Minutes": 61, "laningPhaseGoldExpAdvantage": 0, "legendaryCount": 1, "lostAnInhibitor": 1, "maxCsAdvantageOnLaneOpponent": 16, "maxKillDeficit": 1, "maxLevelLeadLaneOpponent": 2, "mejaisFullStackInTime": 0, "moreEnemyJungleThanOpponent": 0, "multiKillOneSpell": 0, "multiTurretRiftHeraldCount": 0, "multikills": 1, "multikillsAfterAggressiveFlash": 0, "mythicItemUsed": 6630, "outerTurretExecutesBefore10Minutes": 0, "outnumberedKills": 1, "outnumberedNexusKill": 0, "perfectDragonSoulsTaken": 0, "perfectGame": 0, "pickKillWithAlly": 11, "playedChampSelectPosition": 1, "poroExplosions": 0, "quickCleanse": 0, "quickFirstTurret": 0, "quickSoloKills": 0, "riftHeraldTakedowns": 0, "saveAllyFromDeath": 0, "scuttleCrabKills": 1, "skillshotsDodged": 37, "skillshotsHit": 30, "snowballsHit": 0, "soloBaronKills": 0, "soloKills": 3, "stealthWardsPlaced": 8, "survivedSingleDigitHpCount": 0, "survivedThreeImmobilizesInFight": 4, "takedownOnFirstTurret": 1, "takedowns": 14, "takedownsAfterGainingLevelAdvantage": 0, "takedownsBeforeJungleMinionSpawn": 0, "takedownsFirstXMinutes": 6, "takedownsInAlcove": 0, "takedownsInEnemyFountain": 0, "teamBaronKills": 1, "teamDamagePercentage": 0.26511385475621596, "teamElderDragonKills": 0, "teamRiftHeraldKills": 2, "tookLargeDamageSurvived": 0, "turretPlatesTaken": 5, "turretTakedowns": 4, "turretsTakenWithRiftHerald": 5, "twentyMinionsIn3SecondsCount": 0, "twoWardsOneSweeperCount": 0, "unseenRecalls": 0, "visionScoreAdvantageLaneOpponent": 0.6699826717376709, "visionScorePerMinute": 0.7407901072278279, "wardTakedowns": 3, "wardTakedownsBefore20M": 2, "wardsGuarded": 0}, "champExperience": 17383, "champLevel": 17, "championId": 6, "championName": "Urgot", "championTransform": 0, "commandPings": 0, "consumablesPurchased": 1, "damageDealtToBuildings": 5467, "damageDealtToObjectives": 14320, "damageDealtToTurrets": 5467, "damageSelfMitigated": 39503, "dangerPings": 0, "deaths": 0, "detectorWardsPlaced": 0, "doubleKills": 1, "dragonKills": 1, "eligibleForProgression": true, "enemyMissingPings": 2, "enemyVisionPings": 0, "firstBloodAssist": false, "firstBloodKill": false, "firstTowerAssist": false, "firstTowerKill": true, "gameEndedInEarlySurrender": false, "gameEndedInSurrender": false, "getBackPings": 0, "goldEarned": 15579, "goldSpent": 11700, "holdPings": 0, "individualPosition": "TOP", "inhibitorKills": 1, "inhibitorTakedowns": 1, "inhibitorsLost": 1, "item0": 6630, "item1": 2031, "item2": 3181, "item3": 3748, "item4": 3047, "item5": 1054, "item6": 3340, "itemsPurchased": 15, "killingSprees": 1, "kills": 12, "lane": "MIDDLE", "largestCriticalStrike": 0, "largestKillingSpree": 12, "largestMultiKill": 2, "longestTimeSpentLiving": 1703, "magicDamageDealt": 0, "magicDamageDealtToChampions": 0, "magicDamageTaken": 12540, "missions": {"playerScore0": 0, "playerScore1": 0, "playerScore10": 0, "playerScore11": 0, "playerScore2": 0, "playerScore3": 0, "playerScore4": 0, "playerScore5": 0, "playerScore6": 0, "playerScore7": 0, "playerScore8": 0, "playerScore9": 0}, "needVisionPings": 0, "neutralMinionsKilled": 10, "nexusKills": 1, "nexusLost": 0, "nexusTakedowns": 1, "objectivesStolen": 0, "objectivesStolenAssists": 0, "onMyWayPings": 0, "participantId": 1, "pentaKills": 0, "perks": {"statPerks": {"defense": 5002, "flex": 5002, "offense": 5008}, "styles": [{"description": "primaryStyle", "selections": [{"perk": 8021, "var1": 5518, "var2": 4389, "var3": 0}, {"perk": 9111, "var1": 1418, "var2": 280, "var3": 0}, {"perk": 9105, "var1": 14, "var2": 40, "var3": 0}, {"perk": 8299, "var1": 497, "var2": 0, "var3": 0}], "style": 8000}, {"description": "subStyle", "selections": [{"perk": 8446, "var1": 2224, "var2": 0, "var3": 0}, {"perk": 8444, "var1": 2242, "var2": 0, "var3": 0}], "style": 8400}]}, "physicalDamageDealt": 191070, "physicalDamageDealtToChampions": 23162, "physicalDamageTaken": 18608, "placement": 0, "playerAugment1": 0, "playerAugment2": 0, "playerAugment3": 0, "playerAugment4": 0, "playerScore0": 0, "playerScore1": 0, "playerScore10": 0, "playerScore11": 0, "playerScore2": 0, "playerScore3": 0, "playerScore4": 0, "playerScore5": 0, "playerScore6": 0, "playerScore7": 0, "playerScore8": 0, "playerScore9": 0, "playerSubteamId": 0, "profileIcon": 5367, "pushPings": 1, "puuid": "SS0I_KzXcaR7hS4l5pCxl5PMsfVO2EYbcIYkEg1OHE8J3GBNL8EmeKaQUYcywvtM-qYDeUP2A2WyFw", "quadraKills": 0, "riotIdName": "", "riotIdTagline": "", "role": "DUO", "sightWardsBoughtInGame": 0, "spell1Casts": 44, "spell2Casts": 143, "spell3Casts": 50, "spell4Casts": 14, "subteamPlacement": 0, "summoner1Casts": 2, "summoner1Id": 12, "summoner2Casts": 4, "summoner2Id": 4, "summonerId": "pHw5oJs0PVqLWoye0YZNmsJVKZmbyP4xFf7JflVbMsk3ACc", "summonerLevel": 132, "summonerName": "\uc778\uc0dd\uc5b5\uae4c\ub2f9\ud55c\uc0ac\ub78c", "teamEarlySurrendered": false, "teamId": 100, "teamPosition": "TOP", "timeCCingOthers": 45, "timePlayed": 1707, "totalAllyJungleMinionsKilled": 2, "totalDamageDealt": 197154, "totalDamageDealtToChampions": 27002, "totalDamageShieldedOnTeammates": 0, "totalDamageTaken": 32301, "totalEnemyJungleMinionsKilled": 0, "totalHeal": 14318, "totalHealsOnTeammates": 0, "totalMinionsKilled": 211, "totalTimeCCDealt": 431, "totalTimeSpentDead": 0, "totalUnitsHealed": 1, "tripleKills": 0, "trueDamageDealt": 6083, "trueDamageDealtToChampions": 3839, "trueDamageTaken": 1152, "turretKills": 3, "turretTakedowns": 4, "turretsLost": 6, "unrealKills": 0, "visionClearedPings": 0, "visionScore": 21, "visionWardsBoughtInGame": 0, "wardsKilled": 3, "wardsPlaced": 8, "win": true}, {"allInPings": 0, "assistMePings": 3, "assists": 11, "baitPings": 0, "baronKills": 1, "basicPings": 0, "bountyLevel": 0, "challenges": {"12AssistStreakCount": 0, "abilityUses": 199, "acesBefore15Minutes": 0, "alliedJungleMonsterKills": 50, "baronBuffGoldAdvantageOverThreshold": 1, "baronTakedowns": 1, "blastConeOppositeOpponentCount": 0, "bountyGold": 150, "buffsStolen": 2, "completeSupportQuestInTime": 0, "controlWardsPlaced": 1, "damagePerMinute": 462.40513196560084, "damageTakenOnTeamPercentage": 0.21864491814371245, "dancedWithRiftHerald": 0, "deathsByEnemyChamps": 4, "dodgeSkillShotsSmallWindow": 1, "doubleAces": 0, "dragonTakedowns": 1, "earliestBaron": 1532.7408173, "earliestDragonTakedown": 738.4035567999999, "earlyLaningPhaseGoldExpAdvantage": 0, "effectiveHealAndShielding": 0, "elderDragonKillsWithOpposingSoul": 0, "elderDragonMultikills": 0, "enemyChampionImmobilizations": 34, "enemyJungleMonsterKills": 9, "epicMonsterKillsNearEnemyJungler": 1, "epicMonsterKillsWithin30SecondsOfSpawn": 0, "epicMonsterSteals": 0, "epicMonsterStolenWithoutSmite": 0, "firstTurretKilled": 1, "firstTurretKilledTime": 770.0367633, "flawlessAces": 0, "fullTeamTakedown": 0, "gameLength": 1707.9645269999999, "goldPerMinute": 405.9159130702192, "hadOpenNexus": 0, "immobilizeAndKillWithAlly": 6, "initialBuffCount": 2, "initialCrabCount": 1, "jungleCsBefore10Minutes": 48.00000008940697, "junglerKillsEarlyJungle": 0, "junglerTakedownsNearDamagedEpicMonster": 0, "kTurretsDestroyedBeforePlatesFall": 0, "kda": 4.25, "killAfterHiddenWithAlly": 0, "killParticipation": 0.4857142857142857, "killedChampTookFullTeamDamageSurvived": 0, "killingSprees": 1, "killsNearEnemyTurret": 1, "killsOnLanersEarlyJungleAsJungler": 3, "killsOnRecentlyHealedByAramPack": 0, "killsUnderOwnTurret": 1, "killsWithHelpFromEpicMonster": 1, "knockEnemyIntoTeamAndKill": 0, "landSkillShotsEarlyGame": 0, "laneMinionsFirst10Minutes": 4, "laningPhaseGoldExpAdvantage": 0, "legendaryCount": 0, "lostAnInhibitor": 1, "maxCsAdvantageOnLaneOpponent": 19, "maxKillDeficit": 1, "maxLevelLeadLaneOpponent": 2, "mejaisFullStackInTime": 0, "moreEnemyJungleThanOpponent": -21, "multiKillOneSpell": 0, "multiTurretRiftHeraldCount": 0, "multikills": 0, "multikillsAfterAggressiveFlash": 0, "mythicItemUsed": 6691, "outerTurretExecutesBefore10Minutes": 0, "outnumberedKills": 1, "outnumberedNexusKill": 0, "perfectDragonSoulsTaken": 0, "perfectGame": 0, "pickKillWithAlly": 16, "playedChampSelectPosition": 1, "poroExplosions": 0, "quickCleanse": 0, "quickFirstTurret": 0, "quickSoloKills": 0, "riftHeraldTakedowns": 2, "saveAllyFromDeath": 0, "scuttleCrabKills": 4, "skillshotsDodged": 16, "skillshotsHit": 0, "snowballsHit": 0, "soloBaronKills": 0, "soloKills": 1, "stealthWardsPlaced": 1, "survivedSingleDigitHpCount": 0, "survivedThreeImmobilizesInFight": 2, "takedownOnFirstTurret": 0, "takedowns": 17, "takedownsAfterGainingLevelAdvantage": 0, "takedownsBeforeJungleMinionSpawn": 0, "takedownsFirstXMinutes": 10, "takedownsInAlcove": 1, "takedownsInEnemyFountain": 0, "teamBaronKills": 1, "teamDamagePercentage": 0.129235557608343, "teamElderDragonKills": 0, "teamRiftHeraldKills": 2, "tookLargeDamageSurvived": 0, "turretPlatesTaken": 2, "turretTakedowns": 1, "turretsTakenWithRiftHerald": 5, "twentyMinionsIn3SecondsCount": 0, "twoWardsOneSweeperCount": 0, "unseenRecalls": 0, "visionScoreAdvantageLaneOpponent": 0.3959672451019287, "visionScorePerMinute": 0.9427014474018214, "wardTakedowns": 4, "wardTakedownsBefore20M": 4, "wardsGuarded": 0}, "champExperience": 12499, "champLevel": 14, "championId": 35, "championName": "Shaco", "championTransform": 0, "commandPings": 21, "consumablesPurchased": 2, "damageDealtToBuildings": 1069, "damageDealtToObjectives": 34409, "damageDealtToTurrets": 1069, "damageSelfMitigated": 14103, "dangerPings": 0, "deaths": 4, "detectorWardsPlaced": 1, "doubleKills": 0, "dragonKills": 1, "eligibleForProgression": true, "enemyMissingPings": 3, "enemyVisionPings": 0, "firstBloodAssist": true, "firstBloodKill": false, "firstTowerAssist": false, "firstTowerKill": false, "gameEndedInEarlySurrender": false, "gameEndedInSurrender": false, "getBackPings": 1, "goldEarned": 11554, "goldSpent": 10925, "holdPings": 0, "individualPosition": "JUNGLE", "inhibitorKills": 0, "inhibitorTakedowns": 0, "inhibitorsLost": 1, "item0": 0, "item1": 0, "item2": 3033, "item3": 6691, "item4": 6693, "item5": 3158, "item6": 3364, "itemsPurchased": 19, "killingSprees": 2, "kills": 6, "lane": "JUNGLE", "largestCriticalStrike": 0, "largestKillingSpree": 3, "largestMultiKill": 1, "longestTimeSpentLiving": 598, "magicDamageDealt": 32359, "magicDamageDealtToChampions": 5966, "magicDamageTaken": 4418, "missions": {"playerScore0": 0, "playerScore1": 0, "playerScore10": 0, "playerScore11": 0, "playerScore2": 0, "playerScore3": 0, "playerScore4": 0, "playerScore5": 0, "playerScore6": 0, "playerScore7": 0, "playerScore8": 0, "playerScore9": 0}, "needVisionPings": 0, "neutralMinionsKilled": 136, "nexusKills": 0, "nexusLost": 0, "nexusTakedowns": 0, "objectivesStolen": 0, "objectivesStolenAssists": 0, "onMyWayPings": 38, "participantId": 2, "pentaKills": 0, "perks": {"statPerks": {"defense": 5002, "flex": 5008, "offense": 5005}, "styles": [{"description": "primaryStyle", "selections": [{"perk": 9923, "var1": 31, "var2": 73, "var3": 0}, {"perk": 8143, "var1": 480, "var2": 0, "var3": 0}, {"perk": 8138, "var1": 18, "var2": 0, "var3": 0}, {"perk": 8105, "var1": 13, "var2": 5, "var3": 0}], "style": 8100}, {"description": "subStyle", "selections": [{"perk": 8014, "var1": 357, "var2": 0, "var3": 0}, {"perk": 9104, "var1": 9, "var2": 10, "var3": 0}], "style": 8000}]}, "physicalDamageDealt": 99935, "physicalDamageDealtToChampions": 5479, "physicalDamageTaken": 20138, "placement": 0, "playerAugment1": 0, "playerAugment2": 0, "playerAugment3": 0, "playerAugment4": 0, "playerScore0": 0, "playerScore1": 0, "playerScore10": 0, "playerScore11": 0, "playerScore2": 0, "playerScore3": 0, "playerScore4": 0, "playerScore5": 0, "playerScore6": 0, "playerScore7": 0, "playerScore8": 0, "playerScore9": 0, "playerSubteamId": 0, "profileIcon": 5371, "pushPings": 0, "puuid": "OqkL0mf8VRsgWZ0OKAmRzO9y3nXrvwPSR9B8o60hry_8gy2E8XJtPFo3DsDqe03u9935GisPXMauKQ", "quadraKills": 0, "riotIdName": "", "riotIdTagline": "", "role": "NONE", "sightWardsBoughtInGame": 0, "spell1Casts": 51, "spell2Casts": 64, "spell3Casts": 73, "spell4Casts": 11, "subteamPlacement": 0, "summoner1Casts": 6, "summoner1Id": 14, "summoner2Casts": 16, "summoner2Id": 11, "summonerId": "JrW-_PKF9GwXd_eXBvalQ9NlJDUQxq5UHKu4iDQBinh_YUo", "summonerLevel": 186, "summonerName": "\uba54\ub974\uc138\uc624", "teamEarlySurrendered": false, "teamId": 100, "teamPosition": "JUNGLE", "timeCCingOthers": 19, "timePlayed": 1707, "totalAllyJungleMinionsKilled": 83, "totalDamageDealt": 174008, "totalDamageDealtToChampions": 13162, "totalDamageShieldedOnTeammates": 0, "totalDamageTaken": 24770, "totalEnemyJungleMinionsKilled": 16, "totalHeal": 12904, "totalHealsOnTeammates": 0, "totalMinionsKilled": 16, "totalTimeCCDealt": 674, "totalTimeSpentDead": 131, "totalUnitsHealed": 1, "tripleKills": 0, "trueDamageDealt": 41712, "trueDamageDealtToChampions": 1716, "trueDamageTaken": 213, "turretKills": 1, "turretTakedowns": 1, "turretsLost": 6, "unrealKills": 0, "visionClearedPings": 0, "visionScore": 26, "visionWardsBoughtInGame": 1, "wardsKilled": 4, "wardsPlaced": 2, "win": true}, {"allInPings": 0, "assistMePings": 1, "assists": 7, "baitPings": 0, "baronKills": 0, "basicPings": 0, "bountyLevel": 0, "challenges": {"12AssistStreakCount": 0, "abilityUses": 127, "acesBefore15Minutes": 0, "alliedJungleMonsterKills": 1, "baronBuffGoldAdvantageOverThreshold": 1, "baronTakedowns": 0, "blastConeOppositeOpponentCount": 0, "bountyGold": 0, "buffsStolen": 0, "completeSupportQuestInTime": 0, "controlWardTimeCoverageInRiverOrEnemyHalf": 0.8582887547289207, "controlWardsPlaced": 5, "damagePerMinute": 640.3061070058747, "damageTakenOnTeamPercentage": 0.23202726395698153, "dancedWithRiftHerald": 0, "deathsByEnemyChamps": 9, "dodgeSkillShotsSmallWindow": 0, "doubleAces": 0, "dragonTakedowns": 0, "earliestBaron": 1532.7408173, "earlyLaningPhaseGoldExpAdvantage": 0, "effectiveHealAndShielding": 0, "elderDragonKillsWithOpposingSoul": 0, "elderDragonMultikills": 0, "enemyChampionImmobilizations": 0, "enemyJungleMonsterKills": 0, "epicMonsterKillsNearEnemyJungler": 0, "epicMonsterKillsWithin30SecondsOfSpawn": 0, "epicMonsterSteals": 0, "epicMonsterStolenWithoutSmite": 0, "firstTurretKilled": 1, "firstTurretKilledTime": 770.0367633, "flawlessAces": 0, "fullTeamTakedown": 0, "gameLength": 1707.9645269999999, "getTakedownsInAllLanesEarlyJungleAsLaner": 0, "goldPerMinute": 374.8101848019236, "hadOpenNexus": 0, "immobilizeAndKillWithAlly": 0, "initialBuffCount": 0, "initialCrabCount": 0, "jungleCsBefore10Minutes": 0, "junglerTakedownsNearDamagedEpicMonster": 0, "kTurretsDestroyedBeforePlatesFall": 0, "kda": 1.2222222222222223, "killAfterHiddenWithAlly": 0, "killParticipation": 0.3142857142857143, "killedChampTookFullTeamDamageSurvived": 0, "killingSprees": 1, "killsNearEnemyTurret": 2, "killsOnOtherLanesEarlyJungleAsLaner": 0, "killsOnRecentlyHealedByAramPack": 0, "killsUnderOwnTurret": 0, "killsWithHelpFromEpicMonster": 0, "knockEnemyIntoTeamAndKill": 0, "landSkillShotsEarlyGame": 0, "laneMinionsFirst10Minutes": 58, "laningPhaseGoldExpAdvantage": 0, "legendaryCount": 0, "lostAnInhibitor": 1, "maxCsAdvantageOnLaneOpponent": 15, "maxKillDeficit": 1, "maxLevelLeadLaneOpponent": 1, "mejaisFullStackInTime": 0, "moreEnemyJungleThanOpponent": 0, "multiKillOneSpell": 0, "multiTurretRiftHeraldCount": 0, "multikills": 0, "multikillsAfterAggressiveFlash": 0, "mythicItemUsed": 3152, "outerTurretExecutesBefore10Minutes": 0, "outnumberedKills": 0, "outnumberedNexusKill": 0, "perfectDragonSoulsTaken": 0, "perfectGame": 0, "pickKillWithAlly": 10, "playedChampSelectPosition": 1, "poroExplosions": 0, "quickCleanse": 0, "quickFirstTurret": 0, "quickSoloKills": 0, "riftHeraldTakedowns": 0, "saveAllyFromDeath": 0, "scuttleCrabKills": 1, "skillshotsDodged": 17, "skillshotsHit": 0, "snowballsHit": 0, "soloBaronKills": 0, "soloKills": 1, "stealthWardsPlaced": 0, "survivedSingleDigitHpCount": 0, "survivedThreeImmobilizesInFight": 2, "takedownOnFirstTurret": 0, "takedowns": 11, "takedownsAfterGainingLevelAdvantage": 0, "takedownsBeforeJungleMinionSpawn": 0, "takedownsFirstXMinutes": 8, "takedownsInAlcove": 0, "takedownsInEnemyFountain": 0, "teamBaronKills": 1, "teamDamagePercentage": 0.17895631137823853, "teamElderDragonKills": 0, "teamRiftHeraldKills": 2, "tookLargeDamageSurvived": 0, "turretPlatesTaken": 2, "turretTakedowns": 0, "turretsTakenWithRiftHerald": 5, "twentyMinionsIn3SecondsCount": 0, "twoWardsOneSweeperCount": 0, "unseenRecalls": 0, "visionScoreAdvantageLaneOpponent": -0.11227566003799438, "visionScorePerMinute": 0.5507391260533925, "wardTakedowns": 1, "wardTakedownsBefore20M": 1, "wardsGuarded": 0}, "champExperience": 13277, "champLevel": 15, "championId": 55, "championName": "Katarina", "championTransform": 0, "commandPings": 14, "consumablesPurchased": 7, "damageDealtToBuildings": 447, "damageDealtToObjectives": 447, "damageDealtToTurrets": 447, "damageSelfMitigated": 16232, "dangerPings": 0, "deaths": 9, "detectorWardsPlaced": 5, "doubleKills": 0, "dragonKills": 0, "eligibleForProgression": true, "enemyMissingPings": 0, "enemyVisionPings": 0, "firstBloodAssist": false, "firstBloodKill": true, "firstTowerAssist": false, "firstTowerKill": false, "gameEndedInEarlySurrender": false, "gameEndedInSurrender": false, "getBackPings": 0, "goldEarned": 10669, "goldSpent": 10050, "holdPings": 0, "individualPosition": "MIDDLE", "inhibitorKills": 0, "inhibitorTakedowns": 0, "inhibitorsLost": 1, "item0": 3152, "item1": 3115, "item2": 2055, "item3": 3020, "item4": 1082, "item5": 1058, "item6": 3364, "itemsPurchased": 21, "killingSprees": 1, "kills": 4, "lane": "MIDDLE", "largestCriticalStrike": 0, "largestKillingSpree": 3, "largestMultiKill": 1, "longestTimeSpentLiving": 559, "magicDamageDealt": 120704, "magicDamageDealtToChampions": 16285, "magicDamageTaken": 3267, "missions": {"playerScore0": 0, "playerScore1": 0, "playerScore10": 0, "playerScore11": 0, "playerScore2": 0, "playerScore3": 0, "playerScore4": 0, "playerScore5": 0, "playerScore6": 0, "playerScore7": 0, "playerScore8": 0, "playerScore9": 0}, "needVisionPings": 0, "neutralMinionsKilled": 6, "nexusKills": 0, "nexusLost": 0, "nexusTakedowns": 0, "objectivesStolen": 0, "objectivesStolenAssists": 0, "onMyWayPings": 19, "participantId": 3, "pentaKills": 0, "perks": {"statPerks": {"defense": 5002, "flex": 5008, "offense": 5008}, "styles": [{"description": "primaryStyle", "selections": [{"perk": 8112, "var1": 1347, "var2": 0, "var3": 0}, {"perk": 8143, "var1": 830, "var2": 0, "var3": 0}, {"perk": 8138, "var1": 30, "var2": 0, "var3": 0}, {"perk": 8105, "var1": 8, "var2": 3, "var3": 0}], "style": 8100}, {"description": "subStyle", "selections": [{"perk": 8014, "var1": 286, "var2": 0, "var3": 0}, {"perk": 9111, "var1": 627, "var2": 220, "var3": 0}], "style": 8000}]}, "physicalDamageDealt": 10576, "physicalDamageDealtToChampions": 1045, "physicalDamageTaken": 21256, "placement": 0, "playerAugment1": 0, "playerAugment2": 0, "playerAugment3": 0, "playerAugment4": 0, "playerScore0": 0, "playerScore1": 0, "playerScore10": 0, "playerScore11": 0, "playerScore2": 0, "playerScore3": 0, "playerScore4": 0, "playerScore5": 0, "playerScore6": 0, "playerScore7": 0, "playerScore8": 0, "playerScore9": 0, "playerSubteamId": 0, "profileIcon": 4568, "pushPings": 0, "puuid": "dwu7JEPK-98Kn7XncFjtZxqQCREu1eTyH6wD4jpU4FgrLYjcqAAzWG3JsBQgLX6BUOxODN93DFQw7w", "quadraKills": 0, "riotIdName": "", "riotIdTagline": "", "role": "DUO", "sightWardsBoughtInGame": 0, "spell1Casts": 75, "spell2Casts": 41, "spell3Casts": 0, "spell4Casts": 11, "subteamPlacement": 0, "summoner1Casts": 4, "summoner1Id": 4, "summoner2Casts": 6, "summoner2Id": 14, "summonerId": "2BbFztObagWi3xwEn66_w8-jSQcmLPqw3sIC5wCaF9dm0iU", "summonerLevel": 434, "summonerName": "\ud788\uad6c\ub8e8\ub9c8 ", "teamEarlySurrendered": false, "teamId": 100, "teamPosition": "MIDDLE", "timeCCingOthers": 0, "timePlayed": 1707, "totalAllyJungleMinionsKilled": 2, "totalDamageDealt": 132177, "totalDamageDealtToChampions": 18227, "totalDamageShieldedOnTeammates": 0, "totalDamageTaken": 26286, "totalEnemyJungleMinionsKilled": 0, "totalHeal": 2910, "totalHealsOnTeammates": 0, "totalMinionsKilled": 185, "totalTimeCCDealt": 1, "totalTimeSpentDead": 253, "totalUnitsHealed": 1, "tripleKills": 0, "trueDamageDealt": 896, "trueDamageDealtToChampions": 896, "trueDamageTaken": 1762, "turretKills": 0, "turretTakedowns": 0, "turretsLost": 6, "unrealKills": 0, "visionClearedPings": 0, "visionScore": 15, "visionWardsBoughtInGame": 6, "wardsKilled": 1, "wardsPlaced": 5, "win": true}, {"allInPings": 0, "assistMePings": 2, "assists": 4, "baitPings": 0, "baronKills": 0, "basicPings": 0, "bountyLevel": 3, "challenges": {"12AssistStreakCount": 0, "abilityUses": 145, "acesBefore15Minutes": 0, "alliedJungleMonsterKills": 0, "baronBuffGoldAdvantageOverThreshold": 1, "baronTakedowns": 1, "blastConeOppositeOpponentCount": 0, "bountyGold": 0, "buffsStolen": 0, "completeSupportQuestInTime": 0, "controlWardTimeCoverageInRiverOrEnemyHalf": 0.39392060962868, "controlWardsPlaced": 2, "damagePerMinute": 861.6578573048432, "damageTakenOnTeamPercentage": 0.16177273266918457, "dancedWithRiftHerald": 0, "deathsByEnemyChamps": 5, "dodgeSkillShotsSmallWindow": 1, "doubleAces": 0, "dragonTakedowns": 1, "earliestBaron": 1532.7408173, "earliestDragonTakedown": 1421.3926979, "earlyLaningPhaseGoldExpAdvantage": 0, "effectiveHealAndShielding": 0, "elderDragonKillsWithOpposingSoul": 0, "elderDragonMultikills": 0, "enemyChampionImmobilizations": 5, "enemyJungleMonsterKills": 3, "epicMonsterKillsNearEnemyJungler": 0, "epicMonsterKillsWithin30SecondsOfSpawn": 0, "epicMonsterSteals": 0, "epicMonsterStolenWithoutSmite": 0, "firstTurretKilled": 1, "firstTurretKilledTime": 770.0367633, "flawlessAces": 0, "fullTeamTakedown": 0, "gameLength": 1707.9645269999999, "getTakedownsInAllLanesEarlyJungleAsLaner": 0, "goldPerMinute": 476.83825931781195, "hadOpenNexus": 0, "immobilizeAndKillWithAlly": 0, "initialBuffCount": 0, "initialCrabCount": 0, "jungleCsBefore10Minutes": 0, "junglerTakedownsNearDamagedEpicMonster": 0, "kTurretsDestroyedBeforePlatesFall": 0, "kda": 3, "killAfterHiddenWithAlly": 2, "killParticipation": 0.42857142857142855, "killedChampTookFullTeamDamageSurvived": 0, "killingSprees": 2, "killsNearEnemyTurret": 5, "killsOnOtherLanesEarlyJungleAsLaner": 0, "killsOnRecentlyHealedByAramPack": 0, "killsUnderOwnTurret": 0, "killsWithHelpFromEpicMonster": 0, "knockEnemyIntoTeamAndKill": 0, "landSkillShotsEarlyGame": 10, "laneMinionsFirst10Minutes": 68, "laningPhaseGoldExpAdvantage": 1, "legendaryCount": 0, "lostAnInhibitor": 1, "maxCsAdvantageOnLaneOpponent": 44.20000001788139, "maxKillDeficit": 1, "maxLevelLeadLaneOpponent": 3, "mejaisFullStackInTime": 0, "moreEnemyJungleThanOpponent": 0, "multiKillOneSpell": 0, "multiTurretRiftHeraldCount": 0, "multikills": 2, "multikillsAfterAggressiveFlash": 0, "mythicItemUsed": 6671, "outerTurretExecutesBefore10Minutes": 0, "outnumberedKills": 3, "outnumberedNexusKill": 0, "perfectDragonSoulsTaken": 0, "perfectGame": 0, "pickKillWithAlly": 13, "playedChampSelectPosition": 1, "poroExplosions": 0, "quickCleanse": 1, "quickFirstTurret": 0, "quickSoloKills": 0, "riftHeraldTakedowns": 0, "saveAllyFromDeath": 0, "scuttleCrabKills": 1, "skillshotsDodged": 39, "skillshotsHit": 31, "snowballsHit": 0, "soloBaronKills": 0, "soloKills": 2, "soloTurretsLategame": 1, "stealthWardsPlaced": 4, "survivedSingleDigitHpCount": 0, "survivedThreeImmobilizesInFight": 0, "takedownOnFirstTurret": 0, "takedowns": 15, "takedownsAfterGainingLevelAdvantage": 1, "takedownsBeforeJungleMinionSpawn": 0, "takedownsFirstXMinutes": 7, "takedownsInAlcove": 1, "takedownsInEnemyFountain": 0, "teamBaronKills": 1, "teamDamagePercentage": 0.24082092943701475, "teamElderDragonKills": 0, "teamRiftHeraldKills": 2, "tookLargeDamageSurvived": 0, "turretPlatesTaken": 3, "turretTakedowns": 5, "turretsTakenWithRiftHerald": 5, "twentyMinionsIn3SecondsCount": 0, "twoWardsOneSweeperCount": 0, "unseenRecalls": 0, "visionScoreAdvantageLaneOpponent": 0.2690563201904297, "visionScorePerMinute": 0.9109197135797762, "wardTakedowns": 3, "wardTakedownsBefore20M": 2, "wardsGuarded": 0}, "champExperience": 14316, "champLevel": 15, "championId": 51, "championName": "Caitlyn", "championTransform": 0, "commandPings": 13, "consumablesPurchased": 4, "damageDealtToBuildings": 10228, "damageDealtToObjectives": 19815, "damageDealtToTurrets": 10228, "damageSelfMitigated": 8688, "dangerPings": 0, "deaths": 5, "detectorWardsPlaced": 2, "doubleKills": 2, "dragonKills": 0, "eligibleForProgression": true, "enemyMissingPings": 33, "enemyVisionPings": 8, "firstBloodAssist": false, "firstBloodKill": false, "firstTowerAssist": false, "firstTowerKill": false, "gameEndedInEarlySurrender": false, "gameEndedInSurrender": false, "getBackPings": 2, "goldEarned": 13573, "goldSpent": 11200, "holdPings": 0, "individualPosition": "BOTTOM", "inhibitorKills": 0, "inhibitorTakedowns": 1, "inhibitorsLost": 1, "item0": 3006, "item1": 6671, "item2": 1055, "item3": 3094, "item4": 0, "item5": 3095, "item6": 3363, "itemsPurchased": 21, "killingSprees": 4, "kills": 11, "lane": "BOTTOM", "largestCriticalStrike": 1224, "largestKillingSpree": 3, "largestMultiKill": 2, "longestTimeSpentLiving": 450, "magicDamageDealt": 9962, "magicDamageDealtToChampions": 1941, "magicDamageTaken": 6535, "missions": {"playerScore0": 0, "playerScore1": 0, "playerScore10": 0, "playerScore11": 0, "playerScore2": 0, "playerScore3": 0, "playerScore4": 0, "playerScore5": 0, "playerScore6": 0, "playerScore7": 0, "playerScore8": 0, "playerScore9": 0}, "needVisionPings": 0, "neutralMinionsKilled": 5, "nexusKills": 0, "nexusLost": 0, "nexusTakedowns": 1, "objectivesStolen": 0, "objectivesStolenAssists": 0, "onMyWayPings": 9, "participantId": 4, "pentaKills": 0, "perks": {"statPerks": {"defense": 5002, "flex": 5008, "offense": 5005}, "styles": [{"description": "primaryStyle", "selections": [{"perk": 8008, "var1": 41, "var2": 5, "var3": 0}, {"perk": 8009, "var1": 1735, "var2": 0, "var3": 0}, {"perk": 9103, "var1": 21, "var2": 0, "var3": 0}, {"perk": 8014, "var1": 699, "var2": 0, "var3": 0}], "style": 8000}, {"description": "subStyle", "selections": [{"perk": 8233, "var1": 18, "var2": 40, "var3": 0}, {"perk": 8236, "var1": 14, "var2": 0, "var3": 0}], "style": 8200}]}, "physicalDamageDealt": 172697, "physicalDamageDealtToChampions": 22470, "physicalDamageTaken": 11085, "placement": 0, "playerAugment1": 0, "playerAugment2": 0, "playerAugment3": 0, "playerAugment4": 0, "playerScore0": 0, "playerScore1": 0, "playerScore10": 0, "playerScore11": 0, "playerScore2": 0, "playerScore3": 0, "playerScore4": 0, "playerScore5": 0, "playerScore6": 0, "playerScore7": 0, "playerScore8": 0, "playerScore9": 0, "playerSubteamId": 0, "profileIcon": 7, "pushPings": 0, "puuid": "kDQhGtqOg0LIyquTm6_dM93pBlbFT1l3t05HstPYs1Bz1-B0Hi7UF3rVBppD2JTx9JN7LSPgfAbdNw", "quadraKills": 0, "riotIdName": "", "riotIdTagline": "", "role": "SOLO", "sightWardsBoughtInGame": 0, "spell1Casts": 65, "spell2Casts": 43, "spell3Casts": 26, "spell4Casts": 11, "subteamPlacement": 0, "summoner1Casts": 6, "summoner1Id": 1, "summoner2Casts": 4, "summoner2Id": 4, "summonerId": "b-q9gKPGy6dmV0IuKx3CgmiyOAXCRHI9I7CI1Ga2-4PcZTeeZi36hYpOLw", "summonerLevel": 73, "summonerName": "toringee", "teamEarlySurrendered": false, "teamId": 100, "teamPosition": "BOTTOM", "timeCCingOthers": 11, "timePlayed": 1707, "totalAllyJungleMinionsKilled": 0, "totalDamageDealt": 186429, "totalDamageDealtToChampions": 24528, "totalDamageShieldedOnTeammates": 0, "totalDamageTaken": 18327, "totalEnemyJungleMinionsKilled": 1, "totalHeal": 5430, "totalHealsOnTeammates": 0, "totalMinionsKilled": 199, "totalTimeCCDealt": 82, "totalTimeSpentDead": 91, "totalUnitsHealed": 1, "tripleKills": 0, "trueDamageDealt": 3770, "trueDamageDealtToChampions": 116, "trueDamageTaken": 705, "turretKills": 5, "turretTakedowns": 5, "turretsLost": 6, "unrealKills": 0, "visionClearedPings": 0, "visionScore": 25, "visionWardsBoughtInGame": 2, "wardsKilled": 3, "wardsPlaced": 11, "win": true}, {"allInPings": 0, "assistMePings": 0, "assists": 11, "baitPings": 0, "baronKills": 0, "basicPings": 0, "bountyLevel": 0, "challenges": {"12AssistStreakCount": 0, "abilityUses": 317, "acesBefore15Minutes": 0, "alliedJungleMonsterKills": 1, "baronBuffGoldAdvantageOverThreshold": 1, "baronTakedowns": 1, "blastConeOppositeOpponentCount": 0, "bountyGold": 0, "buffsStolen": 0, "completeSupportQuestInTime": 1, "controlWardTimeCoverageInRiverOrEnemyHalf": 0.8398978127606043, "controlWardsPlaced": 4, "damagePerMinute": 665.0552762402308, "damageTakenOnTeamPercentage": 0.1024321230777368, "dancedWithRiftHerald": 0, "deathsByEnemyChamps": 5, "dodgeSkillShotsSmallWindow": 2, "doubleAces": 0, "dragonTakedowns": 1, "earliestBaron": 1532.7408173, "earliestDragonTakedown": 1421.3926979, "earlyLaningPhaseGoldExpAdvantage": 0, "effectiveHealAndShielding": 0, "elderDragonKillsWithOpposingSoul": 0, "elderDragonMultikills": 0, "enemyChampionImmobilizations": 27, "enemyJungleMonsterKills": 1, "epicMonsterKillsNearEnemyJungler": 0, "epicMonsterKillsWithin30SecondsOfSpawn": 0, "epicMonsterSteals": 0, "epicMonsterStolenWithoutSmite": 0, "fasterSupportQuestCompletion": 1, "firstTurretKilled": 1, "firstTurretKilledTime": 770.0367633, "flawlessAces": 0, "fullTeamTakedown": 0, "gameLength": 1707.9645269999999, "getTakedownsInAllLanesEarlyJungleAsLaner": 0, "goldPerMinute": 337.01718585956326, "hadOpenNexus": 0, "highestWardKills": 1, "immobilizeAndKillWithAlly": 6, "initialBuffCount": 0, "initialCrabCount": 0, "jungleCsBefore10Minutes": 0, "junglerTakedownsNearDamagedEpicMonster": 0, "kTurretsDestroyedBeforePlatesFall": 0, "kda": 2.6, "killAfterHiddenWithAlly": 2, "killParticipation": 0.37142857142857144, "killedChampTookFullTeamDamageSurvived": 0, "killingSprees": 0, "killsNearEnemyTurret": 0, "killsOnOtherLanesEarlyJungleAsLaner": 0, "killsOnRecentlyHealedByAramPack": 0, "killsUnderOwnTurret": 0, "killsWithHelpFromEpicMonster": 0, "knockEnemyIntoTeamAndKill": 0, "landSkillShotsEarlyGame": 9, "laneMinionsFirst10Minutes": 3, "laningPhaseGoldExpAdvantage": 0, "legendaryCount": 0, "lostAnInhibitor": 1, "maxCsAdvantageOnLaneOpponent": 16, "maxKillDeficit": 1, "maxLevelLeadLaneOpponent": 2, "mejaisFullStackInTime": 0, "moreEnemyJungleThanOpponent": 0, "multiKillOneSpell": 0, "multiTurretRiftHeraldCount": 0, "multikills": 0, "multikillsAfterAggressiveFlash": 0, "mythicItemUsed": 6653, "outerTurretExecutesBefore10Minutes": 0, "outnumberedKills": 1, "outnumberedNexusKill": 0, "perfectDragonSoulsTaken": 0, "perfectGame": 0, "pickKillWithAlly": 12, "playedChampSelectPosition": 1, "poroExplosions": 0, "quickCleanse": 0, "quickFirstTurret": 0, "quickSoloKills": 0, "riftHeraldTakedowns": 0, "saveAllyFromDeath": 0, "scuttleCrabKills": 0, "skillshotsDodged": 36, "skillshotsHit": 22, "snowballsHit": 0, "soloBaronKills": 0, "soloKills": 1, "stealthWardsPlaced": 24, "survivedSingleDigitHpCount": 0, "survivedThreeImmobilizesInFight": 4, "takedownOnFirstTurret": 0, "takedowns": 13, "takedownsAfterGainingLevelAdvantage": 0, "takedownsBeforeJungleMinionSpawn": 0, "takedownsFirstXMinutes": 7, "takedownsInAlcove": 0, "takedownsInEnemyFountain": 0, "teamBaronKills": 1, "teamDamagePercentage": 0.18587334682018775, "teamElderDragonKills": 0, "teamRiftHeraldKills": 2, "tookLargeDamageSurvived": 0, "turretPlatesTaken": 3, "turretTakedowns": 2, "turretsTakenWithRiftHerald": 5, "twentyMinionsIn3SecondsCount": 0, "twoWardsOneSweeperCount": 0, "unseenRecalls": 0, "visionScoreAdvantageLaneOpponent": 0.4580346345901489, "visionScorePerMinute": 2.655520235399461, "wardTakedowns": 7, "wardTakedownsBefore20M": 5, "wardsGuarded": 0}, "champExperience": 11863, "champLevel": 14, "championId": 143, "championName": "Zyra", "championTransform": 0, "commandPings": 7, "consumablesPurchased": 6, "damageDealtToBuildings": 769, "damageDealtToObjectives": 7516, "damageDealtToTurrets": 769, "damageSelfMitigated": 4434, "dangerPings": 0, "deaths": 5, "detectorWardsPlaced": 4, "doubleKills": 0, "dragonKills": 0, "eligibleForProgression": true, "enemyMissingPings": 14, "enemyVisionPings": 7, "firstBloodAssist": false, "firstBloodKill": false, "firstTowerAssist": false, "firstTowerKill": false, "gameEndedInEarlySurrender": false, "gameEndedInSurrender": false, "getBackPings": 7, "goldEarned": 9593, "goldSpent": 7650, "holdPings": 0, "individualPosition": "UTILITY", "inhibitorKills": 0, "inhibitorTakedowns": 1, "inhibitorsLost": 1, "item0": 6653, "item1": 3853, "item2": 3020, "item3": 1026, "item4": 3916, "item5": 1011, "item6": 3364, "itemsPurchased": 22, "killingSprees": 0, "kills": 2, "lane": "MIDDLE", "largestCriticalStrike": 0, "largestKillingSpree": 0, "largestMultiKill": 1, "longestTimeSpentLiving": 715, "magicDamageDealt": 60534, "magicDamageDealtToChampions": 17767, "magicDamageTaken": 4521, "missions": {"playerScore0": 0, "playerScore1": 0, "playerScore10": 0, "playerScore11": 0, "playerScore2": 0, "playerScore3": 0, "playerScore4": 0, "playerScore5": 0, "playerScore6": 0, "playerScore7": 0, "playerScore8": 0, "playerScore9": 0}, "needVisionPings": 0, "neutralMinionsKilled": 4, "nexusKills": 0, "nexusLost": 0, "nexusTakedowns": 0, "objectivesStolen": 0, "objectivesStolenAssists": 0, "onMyWayPings": 6, "participantId": 5, "pentaKills": 0, "perks": {"statPerks": {"defense": 5002, "flex": 5008, "offense": 5007}, "styles": [{"description": "primaryStyle", "selections": [{"perk": 8229, "var1": 1720, "var2": 0, "var3": 0}, {"perk": 8226, "var1": 250, "var2": 395, "var3": 0}, {"perk": 8210, "var1": 4, "var2": 0, "var3": 0}, {"perk": 8237, "var1": 895, "var2": 0, "var3": 0}], "style": 8200}, {"description": "subStyle", "selections": [{"perk": 8120, "var1": 9, "var2": 30, "var3": 14}, {"perk": 8105, "var1": 10, "var2": 4, "var3": 0}], "style": 8100}]}, "physicalDamageDealt": 3887, "physicalDamageDealtToChampions": 784, "physicalDamageTaken": 6601, "placement": 0, "playerAugment1": 0, "playerAugment2": 0, "playerAugment3": 0, "playerAugment4": 0, "playerScore0": 0, "playerScore1": 0, "playerScore10": 0, "playerScore11": 0, "playerScore2": 0, "playerScore3": 0, "playerScore4": 0, "playerScore5": 0, "playerScore6": 0, "playerScore7": 0, "playerScore8": 0, "playerScore9": 0, "playerSubteamId": 0, "profileIcon": 5227, "pushPings": 0, "puuid": "Vy4lRp1s28kxuawBMEC5Fdn76cvYqrHmXkc4kwsfP0i0hbJXqUfz212YN1Oat-nylR59dsgV9AJNng", "quadraKills": 0, "riotIdName": "", "riotIdTagline": "", "role": "SUPPORT", "sightWardsBoughtInGame": 0, "spell1Casts": 115, "spell2Casts": 128, "spell3Casts": 62, "spell4Casts": 12, "subteamPlacement": 0, "summoner1Casts": 4, "summoner1Id": 4, "summoner2Casts": 5, "summoner2Id": 14, "summonerId": "XPASMoBYtZ_tbdhIn6EjqIXdVP-qR7DOSZcTMH8YSzg_k_Q", "summonerLevel": 320, "summonerName": "\uc9c0\ubd80\uc7a5\ucd9c\uc2e0", "teamEarlySurrendered": false, "teamId": 100, "teamPosition": "UTILITY", "timeCCingOthers": 38, "timePlayed": 1707, "totalAllyJungleMinionsKilled": 0, "totalDamageDealt": 64860, "totalDamageDealtToChampions": 18931, "totalDamageShieldedOnTeammates": 0, "totalDamageTaken": 11604, "totalEnemyJungleMinionsKilled": 4, "totalHeal": 2202, "totalHealsOnTeammates": 0, "totalMinionsKilled": 49, "totalTimeCCDealt": 235, "totalTimeSpentDead": 70, "totalUnitsHealed": 1, "tripleKills": 0, "trueDamageDealt": 438, "trueDamageDealtToChampions": 380, "trueDamageTaken": 482, "turretKills": 0, "turretTakedowns": 2, "turretsLost": 6, "unrealKills": 0, "visionClearedPings": 0, "visionScore": 75, "visionWardsBoughtInGame": 4, "wardsKilled": 7, "wardsPlaced": 28, "win": true}, {"allInPings": 0, "assistMePings": 0, "assists": 3, "baitPings": 0, "baronKills": 0, "basicPings": 0, "bountyLevel": 1, "challenges": {"12AssistStreakCount": 0, "abilityUses": 261, "acesBefore15Minutes": 0, "alliedJungleMonsterKills": 0, "baronTakedowns": 0, "blastConeOppositeOpponentCount": 0, "bountyGold": 0, "buffsStolen": 0, "completeSupportQuestInTime": 0, "controlWardsPlaced": 0, "damagePerMinute": 607.4726162550447, "damageTakenOnTeamPercentage": 0.16078841274940564, "dancedWithRiftHerald": 0, "deathsByEnemyChamps": 4, "dodgeSkillShotsSmallWindow": 0, "doubleAces": 0, "dragonTakedowns": 0, "earlyLaningPhaseGoldExpAdvantage": 0, "effectiveHealAndShielding": 0, "elderDragonKillsWithOpposingSoul": 0, "elderDragonMultikills": 0, "enemyChampionImmobilizations": 6, "enemyJungleMonsterKills": 1, "epicMonsterKillsNearEnemyJungler": 0, "epicMonsterKillsWithin30SecondsOfSpawn": 0, "epicMonsterSteals": 0, "epicMonsterStolenWithoutSmite": 0, "firstTurretKilled": 0, "flawlessAces": 0, "fullTeamTakedown": 0, "gameLength": 1707.9645269999999, "getTakedownsInAllLanesEarlyJungleAsLaner": 0, "goldPerMinute": 390.3283825343757, "hadOpenNexus": 0, "immobilizeAndKillWithAlly": 0, "initialBuffCount": 0, "initialCrabCount": 0, "jungleCsBefore10Minutes": 0, "junglerTakedownsNearDamagedEpicMonster": 0, "kTurretsDestroyedBeforePlatesFall": 0, "kda": 1, "killAfterHiddenWithAlly": 0, "killParticipation": 0.17391304347826086, "killedChampTookFullTeamDamageSurvived": 0, "killingSprees": 0, "killsNearEnemyTurret": 1, "killsOnOtherLanesEarlyJungleAsLaner": 0, "killsOnRecentlyHealedByAramPack": 0, "killsUnderOwnTurret": 0, "killsWithHelpFromEpicMonster": 0, "knockEnemyIntoTeamAndKill": 0, "landSkillShotsEarlyGame": 2, "laneMinionsFirst10Minutes": 67, "laningPhaseGoldExpAdvantage": 0, "legendaryCount": 0, "lostAnInhibitor": 0, "maxCsAdvantageOnLaneOpponent": 32, "maxKillDeficit": 0, "maxLevelLeadLaneOpponent": 1, "mejaisFullStackInTime": 0, "moreEnemyJungleThanOpponent": 0, "multiKillOneSpell": 0, "multiTurretRiftHeraldCount": 0, "multikills": 0, "multikillsAfterAggressiveFlash": 0, "mythicItemUsed": 3078, "outerTurretExecutesBefore10Minutes": 0, "outnumberedKills": 0, "outnumberedNexusKill": 0, "perfectDragonSoulsTaken": 0, "perfectGame": 0, "pickKillWithAlly": 3, "playedChampSelectPosition": 1, "poroExplosions": 0, "quickCleanse": 0, "quickFirstTurret": 0, "quickSoloKills": 0, "riftHeraldTakedowns": 0, "saveAllyFromDeath": 0, "scuttleCrabKills": 0, "skillshotsDodged": 10, "skillshotsHit": 11, "snowballsHit": 0, "soloBaronKills": 0, "soloKills": 1, "soloTurretsLategame": 1, "stealthWardsPlaced": 8, "survivedSingleDigitHpCount": 0, "survivedThreeImmobilizesInFight": 0, "takedownOnFirstTurret": 0, "takedowns": 4, "takedownsAfterGainingLevelAdvantage": 0, "takedownsBeforeJungleMinionSpawn": 0, "takedownsFirstXMinutes": 2, "takedownsInAlcove": 0, "takedownsInEnemyFountain": 0, "teamBaronKills": 0, "teamDamagePercentage": 0.21198829577110095, "teamElderDragonKills": 0, "teamRiftHeraldKills": 0, "tookLargeDamageSurvived": 0, "turretPlatesTaken": 1, "turretTakedowns": 3, "turretsTakenWithRiftHerald": 0, "twentyMinionsIn3SecondsCount": 0, "twoWardsOneSweeperCount": 0, "unseenRecalls": 0, "visionScoreAdvantageLaneOpponent": -0.4011914134025574, "visionScorePerMinute": 0.44359149077994947, "wardTakedowns": 0, "wardTakedownsBefore20M": 0, "wardsGuarded": 0}, "champExperience": 16283, "champLevel": 16, "championId": 83, "championName": "Yorick", "championTransform": 0, "commandPings": 2, "consumablesPurchased": 1, "damageDealtToBuildings": 9383, "damageDealtToObjectives": 10942, "damageDealtToTurrets": 9383, "damageSelfMitigated": 17937, "dangerPings": 0, "deaths": 4, "detectorWardsPlaced": 0, "doubleKills": 0, "dragonKills": 0, "eligibleForProgression": true, "enemyMissingPings": 7, "enemyVisionPings": 0, "firstBloodAssist": false, "firstBloodKill": false, "firstTowerAssist": false, "firstTowerKill": false, "gameEndedInEarlySurrender": false, "gameEndedInSurrender": false, "getBackPings": 0, "goldEarned": 11111, "goldSpent": 9333, "holdPings": 0, "individualPosition": "TOP", "inhibitorKills": 1, "inhibitorTakedowns": 1, "inhibitorsLost": 1, "item0": 1054, "item1": 3078, "item2": 3181, "item3": 3076, "item4": 3047, "item5": 1011, "item6": 3340, "itemsPurchased": 19, "killingSprees": 0, "kills": 1, "lane": "JUNGLE", "largestCriticalStrike": 4, "largestKillingSpree": 0, "largestMultiKill": 1, "longestTimeSpentLiving": 463, "magicDamageDealt": 22924, "magicDamageDealtToChampions": 8372, "magicDamageTaken": 5169, "missions": {"playerScore0": 0, "playerScore1": 0, "playerScore10": 0, "playerScore11": 0, "playerScore2": 0, "playerScore3": 0, "playerScore4": 0, "playerScore5": 0, "playerScore6": 0, "playerScore7": 0, "playerScore8": 0, "playerScore9": 0}, "needVisionPings": 0, "neutralMinionsKilled": 4, "nexusKills": 0, "nexusLost": 1, "nexusTakedowns": 0, "objectivesStolen": 0, "objectivesStolenAssists": 0, "onMyWayPings": 1, "participantId": 6, "pentaKills": 0, "perks": {"statPerks": {"defense": 5001, "flex": 5008, "offense": 5005}, "styles": [{"description": "primaryStyle", "selections": [{"perk": 8229, "var1": 1280, "var2": 0, "var3": 0}, {"perk": 8226, "var1": 250, "var2": 767, "var3": 0}, {"perk": 8210, "var1": 1, "var2": 0, "var3": 0}, {"perk": 8236, "var1": 14, "var2": 0, "var3": 0}], "style": 8200}, {"description": "subStyle", "selections": [{"perk": 8345, "var1": 3, "var2": 0, "var3": 0}, {"perk": 8304, "var1": 10, "var2": 3, "var3": 0}], "style": 8300}]}, "physicalDamageDealt": 157194, "physicalDamageDealtToChampions": 8920, "physicalDamageTaken": 13346, "placement": 0, "playerAugment1": 0, "playerAugment2": 0, "playerAugment3": 0, "playerAugment4": 0, "playerScore0": 0, "playerScore1": 0, "playerScore10": 0, "playerScore11": 0, "playerScore2": 0, "playerScore3": 0, "playerScore4": 0, "playerScore5": 0, "playerScore6": 0, "playerScore7": 0, "playerScore8": 0, "playerScore9": 0, "playerSubteamId": 0, "profileIcon": 4069, "pushPings": 0, "puuid": "QLRveNy3l6G9GmT9i_0Z-K8iDtmADeRDiUMoJj5XaAAWpNjFD2vnyx9uecpZI0tsQUUVIfmy7iRbAg", "quadraKills": 0, "riotIdName": "", "riotIdTagline": "", "role": "NONE", "sightWardsBoughtInGame": 0, "spell1Casts": 178, "spell2Casts": 15, "spell3Casts": 59, "spell4Casts": 9, "subteamPlacement": 0, "summoner1Casts": 2, "summoner1Id": 4, "summoner2Casts": 2, "summoner2Id": 12, "summonerId": "qn31iO4BGr0mnKv9yZY-C9elItR5fKF_WEUGdCrNceh2EXI5gLi5NpqIFQ", "summonerLevel": 199, "summonerName": "\uc1a1\ud6a8\uadfc1", "teamEarlySurrendered": false, "teamId": 200, "teamPosition": "TOP", "timeCCingOthers": 10, "timePlayed": 1707, "totalAllyJungleMinionsKilled": 0, "totalDamageDealt": 208760, "totalDamageDealtToChampions": 17292, "totalDamageShieldedOnTeammates": 0, "totalDamageTaken": 20618, "totalEnemyJungleMinionsKilled": 4, "totalHeal": 5280, "totalHealsOnTeammates": 0, "totalMinionsKilled": 245, "totalTimeCCDealt": 148, "totalTimeSpentDead": 108, "totalUnitsHealed": 1, "tripleKills": 0, "trueDamageDealt": 28641, "trueDamageDealtToChampions": 0, "trueDamageTaken": 2101, "turretKills": 3, "turretTakedowns": 3, "turretsLost": 9, "unrealKills": 0, "visionClearedPings": 0, "visionScore": 12, "visionWardsBoughtInGame": 0, "wardsKilled": 0, "wardsPlaced": 8, "win": false}, {"allInPings": 6, "assistMePings": 4, "assists": 5, "baitPings": 0, "baronKills": 0, "basicPings": 0, "bountyLevel": 0, "challenges": {"12AssistStreakCount": 0, "abilityUses": 218, "acesBefore15Minutes": 0, "alliedJungleMonsterKills": 59, "baronTakedowns": 0, "blastConeOppositeOpponentCount": 0, "bountyGold": 450, "buffsStolen": 1, "completeSupportQuestInTime": 0, "controlWardTimeCoverageInRiverOrEnemyHalf": 0.49334129262041754, "controlWardsPlaced": 3, "damagePerMinute": 954.7634072437619, "damageTakenOnTeamPercentage": 0.4055653766656441, "dancedWithRiftHerald": 0, "deathsByEnemyChamps": 10, "dodgeSkillShotsSmallWindow": 0, "doubleAces": 0, "dragonTakedowns": 2, "earliestDragonTakedown": 388.63081589999996, "earlyLaningPhaseGoldExpAdvantage": 0, "effectiveHealAndShielding": 0, "elderDragonKillsWithOpposingSoul": 0, "elderDragonMultikills": 0, "enemyChampionImmobilizations": 46, "enemyJungleMonsterKills": 7, "epicMonsterKillsNearEnemyJungler": 1, "epicMonsterKillsWithin30SecondsOfSpawn": 0, "epicMonsterSteals": 0, "epicMonsterStolenWithoutSmite": 0, "firstTurretKilled": 0, "flawlessAces": 0, "fullTeamTakedown": 0, "gameLength": 1707.9645269999999, "goldPerMinute": 471.81236865494924, "hadOpenNexus": 0, "highestChampionDamage": 1, "immobilizeAndKillWithAlly": 4, "initialBuffCount": 2, "initialCrabCount": 1, "jungleCsBefore10Minutes": 44.00000002980232, "junglerKillsEarlyJungle": 0, "junglerTakedownsNearDamagedEpicMonster": 0, "kTurretsDestroyedBeforePlatesFall": 0, "kda": 1.7, "killAfterHiddenWithAlly": 0, "killParticipation": 0.7391304347826086, "killedChampTookFullTeamDamageSurvived": 0, "killingSprees": 1, "killsNearEnemyTurret": 1, "killsOnLanersEarlyJungleAsJungler": 4, "killsOnRecentlyHealedByAramPack": 0, "killsUnderOwnTurret": 0, "killsWithHelpFromEpicMonster": 0, "knockEnemyIntoTeamAndKill": 0, "landSkillShotsEarlyGame": 1, "laneMinionsFirst10Minutes": 7, "laningPhaseGoldExpAdvantage": 0, "legendaryCount": 0, "lostAnInhibitor": 0, "maxCsAdvantageOnLaneOpponent": 19.25, "maxKillDeficit": 0, "maxLevelLeadLaneOpponent": 1, "mejaisFullStackInTime": 0, "moreEnemyJungleThanOpponent": -26.500000089406967, "multiKillOneSpell": 0, "multiTurretRiftHeraldCount": 0, "multikills": 3, "multikillsAfterAggressiveFlash": 1, "mythicItemUsed": 6630, "outerTurretExecutesBefore10Minutes": 0, "outnumberedKills": 5, "outnumberedNexusKill": 0, "perfectDragonSoulsTaken": 0, "perfectGame": 0, "pickKillWithAlly": 12, "playedChampSelectPosition": 1, "poroExplosions": 0, "quickCleanse": 0, "quickFirstTurret": 0, "quickSoloKills": 0, "riftHeraldTakedowns": 0, "saveAllyFromDeath": 0, "scuttleCrabKills": 1, "skillshotsDodged": 18, "skillshotsHit": 17, "snowballsHit": 0, "soloBaronKills": 0, "soloKills": 4, "stealthWardsPlaced": 3, "survivedSingleDigitHpCount": 0, "survivedThreeImmobilizesInFight": 4, "takedownOnFirstTurret": 0, "takedowns": 17, "takedownsAfterGainingLevelAdvantage": 0, "takedownsBeforeJungleMinionSpawn": 0, "takedownsFirstXMinutes": 11, "takedownsInAlcove": 0, "takedownsInEnemyFountain": 0, "teamBaronKills": 0, "teamDamagePercentage": 0.3331815495058274, "teamElderDragonKills": 0, "teamRiftHeraldKills": 0, "tookLargeDamageSurvived": 0, "turretPlatesTaken": 3, "turretTakedowns": 0, "turretsTakenWithRiftHerald": 0, "twentyMinionsIn3SecondsCount": 0, "twoWardsOneSweeperCount": 0, "unseenRecalls": 0, "visionScoreAdvantageLaneOpponent": -0.28365081548690796, "visionScorePerMinute": 0.6753034159941781, "wardTakedowns": 1, "wardTakedownsBefore20M": 1, "wardsGuarded": 1}, "champExperience": 13287, "champLevel": 15, "championId": 233, "championName": "Briar", "championTransform": 0, "commandPings": 10, "consumablesPurchased": 4, "damageDealtToBuildings": 1265, "damageDealtToObjectives": 22675, "damageDealtToTurrets": 1265, "damageSelfMitigated": 47629, "dangerPings": 0, "deaths": 10, "detectorWardsPlaced": 3, "doubleKills": 3, "dragonKills": 2, "eligibleForProgression": true, "enemyMissingPings": 0, "enemyVisionPings": 0, "firstBloodAssist": false, "firstBloodKill": false, "firstTowerAssist": false, "firstTowerKill": false, "gameEndedInEarlySurrender": false, "gameEndedInSurrender": false, "getBackPings": 8, "goldEarned": 13430, "goldSpent": 12955, "holdPings": 0, "individualPosition": "JUNGLE", "inhibitorKills": 0, "inhibitorTakedowns": 0, "inhibitorsLost": 1, "item0": 6630, "item1": 3161, "item2": 3133, "item3": 3053, "item4": 3067, "item5": 3006, "item6": 3364, "itemsPurchased": 30, "killingSprees": 4, "kills": 12, "lane": "JUNGLE", "largestCriticalStrike": 0, "largestKillingSpree": 4, "largestMultiKill": 2, "longestTimeSpentLiving": 278, "magicDamageDealt": 12506, "magicDamageDealtToChampions": 1626, "magicDamageTaken": 14983, "missions": {"playerScore0": 0, "playerScore1": 0, "playerScore10": 0, "playerScore11": 0, "playerScore2": 0, "playerScore3": 0, "playerScore4": 0, "playerScore5": 0, "playerScore6": 0, "playerScore7": 0, "playerScore8": 0, "playerScore9": 0}, "needVisionPings": 1, "neutralMinionsKilled": 121, "nexusKills": 0, "nexusLost": 1, "nexusTakedowns": 0, "objectivesStolen": 0, "objectivesStolenAssists": 0, "onMyWayPings": 13, "participantId": 7, "pentaKills": 0, "perks": {"statPerks": {"defense": 5001, "flex": 5008, "offense": 5005}, "styles": [{"description": "primaryStyle", "selections": [{"perk": 8008, "var1": 78, "var2": 20, "var3": 0}, {"perk": 9111, "var1": 1380, "var2": 340, "var3": 0}, {"perk": 9105, "var1": 9, "var2": 10, "var3": 0}, {"perk": 8299, "var1": 1179, "var2": 0, "var3": 0}], "style": 8000}, {"description": "subStyle", "selections": [{"perk": 8304, "var1": 9, "var2": 0, "var3": 0}, {"perk": 8321, "var1": 4, "var2": 0, "var3": 0}], "style": 8300}]}, "physicalDamageDealt": 171733, "physicalDamageDealtToChampions": 24895, "physicalDamageTaken": 34490, "placement": 0, "playerAugment1": 0, "playerAugment2": 0, "playerAugment3": 0, "playerAugment4": 0, "playerScore0": 0, "playerScore1": 0, "playerScore10": 0, "playerScore11": 0, "playerScore2": 0, "playerScore3": 0, "playerScore4": 0, "playerScore5": 0, "playerScore6": 0, "playerScore7": 0, "playerScore8": 0, "playerScore9": 0, "playerSubteamId": 0, "profileIcon": 5662, "pushPings": 0, "puuid": "Aq4YLtm0owrzOJLu39GNZRkP4XolZhluorBpIc-jiFs5WI9DiH3ciys7vcMrg835hG7C4tA78wiDfQ", "quadraKills": 0, "riotIdName": "", "riotIdTagline": "", "role": "NONE", "sightWardsBoughtInGame": 0, "spell1Casts": 41, "spell2Casts": 137, "spell3Casts": 30, "spell4Casts": 10, "subteamPlacement": 0, "summoner1Casts": 14, "summoner1Id": 11, "summoner2Casts": 3, "summoner2Id": 4, "summonerId": "-AX5fzjlu-En4nl28JleH0lHZ4uEfXUdYVdvw7OZRsCQRPS1Rqo788ML1Q", "summonerLevel": 92, "summonerName": "AluCarrd", "teamEarlySurrendered": false, "teamId": 200, "teamPosition": "JUNGLE", "timeCCingOthers": 46, "timePlayed": 1707, "totalAllyJungleMinionsKilled": 92, "totalDamageDealt": 214106, "totalDamageDealtToChampions": 27178, "totalDamageShieldedOnTeammates": 0, "totalDamageTaken": 52007, "totalEnemyJungleMinionsKilled": 10, "totalHeal": 40525, "totalHealsOnTeammates": 0, "totalMinionsKilled": 50, "totalTimeCCDealt": 295, "totalTimeSpentDead": 296, "totalUnitsHealed": 1, "tripleKills": 0, "trueDamageDealt": 29865, "trueDamageDealtToChampions": 656, "trueDamageTaken": 2534, "turretKills": 0, "turretTakedowns": 0, "turretsLost": 9, "unrealKills": 0, "visionClearedPings": 0, "visionScore": 19, "visionWardsBoughtInGame": 3, "wardsKilled": 1, "wardsPlaced": 6, "win": false}, {"allInPings": 0, "assistMePings": 0, "assists": 2, "baitPings": 0, "baronKills": 0, "basicPings": 0, "bountyLevel": 0, "challenges": {"12AssistStreakCount": 0, "abilityUses": 296, "acesBefore15Minutes": 0, "alliedJungleMonsterKills": 0, "baronTakedowns": 0, "blastConeOppositeOpponentCount": 0, "bountyGold": 600, "buffsStolen": 0, "completeSupportQuestInTime": 0, "controlWardsPlaced": 0, "damagePerMinute": 508.3583720156795, "damageTakenOnTeamPercentage": 0.21071599605050362, "dancedWithRiftHerald": 0, "deathsByEnemyChamps": 10, "dodgeSkillShotsSmallWindow": 0, "doubleAces": 0, "dragonTakedowns": 0, "earlyLaningPhaseGoldExpAdvantage": 0, "effectiveHealAndShielding": 0, "elderDragonKillsWithOpposingSoul": 0, "elderDragonMultikills": 0, "enemyChampionImmobilizations": 23, "enemyJungleMonsterKills": 6, "epicMonsterKillsNearEnemyJungler": 0, "epicMonsterKillsWithin30SecondsOfSpawn": 0, "epicMonsterSteals": 0, "epicMonsterStolenWithoutSmite": 0, "firstTurretKilled": 0, "flawlessAces": 0, "fullTeamTakedown": 0, "gameLength": 1707.9645269999999, "getTakedownsInAllLanesEarlyJungleAsLaner": 0, "goldPerMinute": 432.5418708622864, "hadOpenNexus": 0, "immobilizeAndKillWithAlly": 4, "initialBuffCount": 0, "initialCrabCount": 0, "jungleCsBefore10Minutes": 0, "junglerTakedownsNearDamagedEpicMonster": 0, "kTurretsDestroyedBeforePlatesFall": 1, "kda": 0.7, "killAfterHiddenWithAlly": 0, "killParticipation": 0.30434782608695654, "killedChampTookFullTeamDamageSurvived": 0, "killingSprees": 0, "killsNearEnemyTurret": 1, "killsOnOtherLanesEarlyJungleAsLaner": 0, "killsOnRecentlyHealedByAramPack": 0, "killsUnderOwnTurret": 1, "killsWithHelpFromEpicMonster": 0, "knockEnemyIntoTeamAndKill": 0, "landSkillShotsEarlyGame": 0, "laneMinionsFirst10Minutes": 53, "laningPhaseGoldExpAdvantage": 0, "legendaryCount": 0, "lostAnInhibitor": 0, "maxCsAdvantageOnLaneOpponent": 30.600000023841858, "maxKillDeficit": 0, "maxLevelLeadLaneOpponent": 1, "mejaisFullStackInTime": 0, "moreEnemyJungleThanOpponent": 0, "multiKillOneSpell": 0, "multiTurretRiftHeraldCount": 0, "multikills": 1, "multikillsAfterAggressiveFlash": 0, "outerTurretExecutesBefore10Minutes": 0, "outnumberedKills": 0, "outnumberedNexusKill": 0, "perfectDragonSoulsTaken": 0, "perfectGame": 0, "pickKillWithAlly": 6, "playedChampSelectPosition": 1, "poroExplosions": 0, "quickCleanse": 0, "quickFirstTurret": 0, "quickSoloKills": 0, "riftHeraldTakedowns": 0, "saveAllyFromDeath": 0, "scuttleCrabKills": 1, "skillshotsDodged": 15, "skillshotsHit": 9, "snowballsHit": 0, "soloBaronKills": 0, "soloKills": 0, "stealthWardsPlaced": 4, "survivedSingleDigitHpCount": 0, "survivedThreeImmobilizesInFight": 0, "takedownOnFirstTurret": 0, "takedowns": 7, "takedownsAfterGainingLevelAdvantage": 0, "takedownsBeforeJungleMinionSpawn": 0, "takedownsFirstXMinutes": 4, "takedownsInAlcove": 0, "takedownsInEnemyFountain": 0, "teamBaronKills": 0, "teamDamagePercentage": 0.17740063015339302, "teamElderDragonKills": 0, "teamRiftHeraldKills": 0, "tookLargeDamageSurvived": 0, "turretPlatesTaken": 5, "turretTakedowns": 3, "turretsTakenWithRiftHerald": 0, "twentyMinionsIn3SecondsCount": 0, "twoWardsOneSweeperCount": 0, "unseenRecalls": 0, "visionScoreAdvantageLaneOpponent": 0.12647581100463867, "visionScorePerMinute": 0.6203942869924274, "wardTakedowns": 5, "wardTakedownsBefore20M": 3, "wardsGuarded": 0}, "champExperience": 13294, "champLevel": 15, "championId": 777, "championName": "Yone", "championTransform": 0, "commandPings": 14, "consumablesPurchased": 4, "damageDealtToBuildings": 4780, "damageDealtToObjectives": 6991, "damageDealtToTurrets": 4780, "damageSelfMitigated": 23258, "dangerPings": 0, "deaths": 10, "detectorWardsPlaced": 0, "doubleKills": 1, "dragonKills": 0, "eligibleForProgression": true, "enemyMissingPings": 1, "enemyVisionPings": 0, "firstBloodAssist": false, "firstBloodKill": false, "firstTowerAssist": false, "firstTowerKill": false, "gameEndedInEarlySurrender": false, "gameEndedInSurrender": false, "getBackPings": 3, "goldEarned": 12312, "goldSpent": 12100, "holdPings": 0, "individualPosition": "MIDDLE", "inhibitorKills": 0, "inhibitorTakedowns": 0, "inhibitorsLost": 1, "item0": 1018, "item1": 1036, "item2": 3031, "item3": 6672, "item4": 3006, "item5": 3181, "item6": 3364, "itemsPurchased": 26, "killingSprees": 1, "kills": 5, "lane": "MIDDLE", "largestCriticalStrike": 620, "largestKillingSpree": 2, "largestMultiKill": 2, "longestTimeSpentLiving": 352, "magicDamageDealt": 14838, "magicDamageDealtToChampions": 2325, "magicDamageTaken": 12589, "missions": {"playerScore0": 0, "playerScore1": 0, "playerScore10": 0, "playerScore11": 0, "playerScore2": 0, "playerScore3": 0, "playerScore4": 0, "playerScore5": 0, "playerScore6": 0, "playerScore7": 0, "playerScore8": 0, "playerScore9": 0}, "needVisionPings": 0, "neutralMinionsKilled": 9, "nexusKills": 0, "nexusLost": 1, "nexusTakedowns": 0, "objectivesStolen": 0, "objectivesStolenAssists": 0, "onMyWayPings": 0, "participantId": 8, "pentaKills": 0, "perks": {"statPerks": {"defense": 5003, "flex": 5008, "offense": 5005}, "styles": [{"description": "primaryStyle", "selections": [{"perk": 8008, "var1": 25, "var2": 1, "var3": 0}, {"perk": 9111, "var1": 381, "var2": 140, "var3": 0}, {"perk": 9104, "var1": 16, "var2": 30, "var3": 0}, {"perk": 8299, "var1": 503, "var2": 0, "var3": 0}], "style": 8000}, {"description": "subStyle", "selections": [{"perk": 8444, "var1": 973, "var2": 0, "var3": 0}, {"perk": 8451, "var1": 205, "var2": 0, "var3": 0}], "style": 8400}]}, "physicalDamageDealt": 139601, "physicalDamageDealtToChampions": 9738, "physicalDamageTaken": 13045, "placement": 0, "playerAugment1": 0, "playerAugment2": 0, "playerAugment3": 0, "playerAugment4": 0, "playerScore0": 0, "playerScore1": 0, "playerScore10": 0, "playerScore11": 0, "playerScore2": 0, "playerScore3": 0, "playerScore4": 0, "playerScore5": 0, "playerScore6": 0, "playerScore7": 0, "playerScore8": 0, "playerScore9": 0, "playerSubteamId": 0, "profileIcon": 4568, "pushPings": 0, "puuid": "XPQ59AkWr0BfSsB9vBnZKvbSahQh5Ikv7XPy_tqzsD8u03jKOY7jARIzl5pG1cyyiLh1_Wd6PAHk0g", "quadraKills": 0, "riotIdName": "", "riotIdTagline": "", "role": "SOLO", "sightWardsBoughtInGame": 0, "spell1Casts": 223, "spell2Casts": 38, "spell3Casts": 27, "spell4Casts": 8, "subteamPlacement": 0, "summoner1Casts": 3, "summoner1Id": 4, "summoner2Casts": 5, "summoner2Id": 14, "summonerId": "Yl0npxk3hK8MCH-Fcr6cwdeNVe9qn3GlUEObVH_7ilkR5uw", "summonerLevel": 254, "summonerName": "\ubb34\ub11d\ub9ac", "teamEarlySurrendered": false, "teamId": 200, "teamPosition": "MIDDLE", "timeCCingOthers": 14, "timePlayed": 1707, "totalAllyJungleMinionsKilled": 0, "totalDamageDealt": 162884, "totalDamageDealtToChampions": 14470, "totalDamageShieldedOnTeammates": 0, "totalDamageTaken": 27021, "totalEnemyJungleMinionsKilled": 4, "totalHeal": 3104, "totalHealsOnTeammates": 0, "totalMinionsKilled": 195, "totalTimeCCDealt": 125, "totalTimeSpentDead": 223, "totalUnitsHealed": 1, "tripleKills": 0, "trueDamageDealt": 8444, "trueDamageDealtToChampions": 2406, "trueDamageTaken": 1386, "turretKills": 3, "turretTakedowns": 3, "turretsLost": 9, "unrealKills": 0, "visionClearedPings": 0, "visionScore": 17, "visionWardsBoughtInGame": 0, "wardsKilled": 5, "wardsPlaced": 4, "win": false}, {"allInPings": 0, "assistMePings": 1, "assists": 4, "baitPings": 0, "baronKills": 0, "basicPings": 0, "bountyLevel": 0, "challenges": {"12AssistStreakCount": 0, "abilityUses": 104, "acesBefore15Minutes": 0, "alliedJungleMonsterKills": 0, "baronTakedowns": 0, "blastConeOppositeOpponentCount": 0, "bountyGold": 0, "buffsStolen": 0, "completeSupportQuestInTime": 0, "controlWardsPlaced": 0, "damagePerMinute": 187.10273482417298, "damageTakenOnTeamPercentage": 0.11888598645015538, "dancedWithRiftHerald": 0, "deathsByEnemyChamps": 5, "dodgeSkillShotsSmallWindow": 0, "doubleAces": 0, "dragonTakedowns": 2, "earliestDragonTakedown": 388.63081589999996, "earlyLaningPhaseGoldExpAdvantage": 0, "effectiveHealAndShielding": 0, "elderDragonKillsWithOpposingSoul": 0, "elderDragonMultikills": 0, "enemyChampionImmobilizations": 4, "enemyJungleMonsterKills": 0, "epicMonsterKillsNearEnemyJungler": 0, "epicMonsterKillsWithin30SecondsOfSpawn": 0, "epicMonsterSteals": 0, "epicMonsterStolenWithoutSmite": 0, "firstTurretKilled": 0, "flawlessAces": 0, "fullTeamTakedown": 0, "gameLength": 1707.9645269999999, "getTakedownsInAllLanesEarlyJungleAsLaner": 0, "goldPerMinute": 314.4963749845784, "hadOpenNexus": 0, "immobilizeAndKillWithAlly": 1, "initialBuffCount": 0, "initialCrabCount": 0, "jungleCsBefore10Minutes": 0, "junglerTakedownsNearDamagedEpicMonster": 0, "kTurretsDestroyedBeforePlatesFall": 0, "kda": 1.4, "killAfterHiddenWithAlly": 2, "killParticipation": 0.30434782608695654, "killedChampTookFullTeamDamageSurvived": 0, "killingSprees": 0, "killsNearEnemyTurret": 1, "killsOnOtherLanesEarlyJungleAsLaner": 0, "killsOnRecentlyHealedByAramPack": 0, "killsUnderOwnTurret": 0, "killsWithHelpFromEpicMonster": 0, "knockEnemyIntoTeamAndKill": 0, "landSkillShotsEarlyGame": 7, "laneMinionsFirst10Minutes": 51, "laningPhaseGoldExpAdvantage": 0, "legendaryCount": 0, "lostAnInhibitor": 0, "maxCsAdvantageOnLaneOpponent": 1, "maxKillDeficit": 0, "maxLevelLeadLaneOpponent": 1, "mejaisFullStackInTime": 0, "moreEnemyJungleThanOpponent": 0, "multiKillOneSpell": 0, "multiTurretRiftHeraldCount": 0, "multikills": 1, "multikillsAfterAggressiveFlash": 1, "outerTurretExecutesBefore10Minutes": 0, "outnumberedKills": 0, "outnumberedNexusKill": 0, "perfectDragonSoulsTaken": 0, "perfectGame": 0, "pickKillWithAlly": 7, "playedChampSelectPosition": 1, "poroExplosions": 0, "quickCleanse": 0, "quickFirstTurret": 0, "quickSoloKills": 0, "riftHeraldTakedowns": 0, "saveAllyFromDeath": 0, "scuttleCrabKills": 0, "skillshotsDodged": 11, "skillshotsHit": 29, "snowballsHit": 0, "soloBaronKills": 0, "soloKills": 0, "stealthWardsPlaced": 8, "survivedSingleDigitHpCount": 0, "survivedThreeImmobilizesInFight": 0, "takedownOnFirstTurret": 0, "takedowns": 7, "takedownsAfterGainingLevelAdvantage": 0, "takedownsBeforeJungleMinionSpawn": 0, "takedownsFirstXMinutes": 6, "takedownsInAlcove": 2, "takedownsInEnemyFountain": 0, "teamBaronKills": 0, "teamDamagePercentage": 0.06529280304683902, "teamElderDragonKills": 0, "teamRiftHeraldKills": 0, "tookLargeDamageSurvived": 0, "turretPlatesTaken": 2, "turretTakedowns": 0, "turretsTakenWithRiftHerald": 0, "twentyMinionsIn3SecondsCount": 0, "twoWardsOneSweeperCount": 0, "unseenRecalls": 0, "visionScoreAdvantageLaneOpponent": -0.2120128870010376, "visionScorePerMinute": 0.7177929683508819, "wardTakedowns": 2, "wardTakedownsBefore20M": 2, "wardsGuarded": 0}, "champExperience": 10116, "champLevel": 13, "championId": 22, "championName": "Ashe", "championTransform": 0, "commandPings": 6, "consumablesPurchased": 2, "damageDealtToBuildings": 1641, "damageDealtToObjectives": 6185, "damageDealtToTurrets": 1641, "damageSelfMitigated": 8309, "dangerPings": 0, "deaths": 5, "detectorWardsPlaced": 0, "doubleKills": 1, "dragonKills": 0, "eligibleForProgression": true, "enemyMissingPings": 3, "enemyVisionPings": 0, "firstBloodAssist": false, "firstBloodKill": false, "firstTowerAssist": false, "firstTowerKill": false, "gameEndedInEarlySurrender": false, "gameEndedInSurrender": false, "getBackPings": 3, "goldEarned": 8952, "goldSpent": 8700, "holdPings": 0, "individualPosition": "BOTTOM", "inhibitorKills": 0, "inhibitorTakedowns": 0, "inhibitorsLost": 1, "item0": 2031, "item1": 3006, "item2": 6672, "item3": 3124, "item4": 1043, "item5": 0, "item6": 3363, "itemsPurchased": 21, "killingSprees": 1, "kills": 3, "lane": "BOTTOM", "largestCriticalStrike": 185, "largestKillingSpree": 2, "largestMultiKill": 2, "longestTimeSpentLiving": 731, "magicDamageDealt": 4876, "magicDamageDealtToChampions": 722, "magicDamageTaken": 6159, "missions": {"playerScore0": 0, "playerScore1": 0, "playerScore10": 0, "playerScore11": 0, "playerScore2": 0, "playerScore3": 0, "playerScore4": 0, "playerScore5": 0, "playerScore6": 0, "playerScore7": 0, "playerScore8": 0, "playerScore9": 0}, "needVisionPings": 0, "neutralMinionsKilled": 0, "nexusKills": 0, "nexusLost": 1, "nexusTakedowns": 0, "objectivesStolen": 0, "objectivesStolenAssists": 0, "onMyWayPings": 14, "participantId": 9, "pentaKills": 0, "perks": {"statPerks": {"defense": 5002, "flex": 5008, "offense": 5005}, "styles": [{"description": "primaryStyle", "selections": [{"perk": 8008, "var1": 12, "var2": 1, "var3": 0}, {"perk": 8009, "var1": 554, "var2": 0, "var3": 0}, {"perk": 9103, "var1": 25, "var2": 10, "var3": 0}, {"perk": 8014, "var1": 91, "var2": 0, "var3": 0}], "style": 8000}, {"description": "subStyle", "selections": [{"perk": 8345, "var1": 3, "var2": 0, "var3": 0}, {"perk": 8410, "var1": 47, "var2": 0, "var3": 0}], "style": 8300}]}, "physicalDamageDealt": 84760, "physicalDamageDealtToChampions": 4603, "physicalDamageTaken": 8622, "placement": 0, "playerAugment1": 0, "playerAugment2": 0, "playerAugment3": 0, "playerAugment4": 0, "playerScore0": 0, "playerScore1": 0, "playerScore10": 0, "playerScore11": 0, "playerScore2": 0, "playerScore3": 0, "playerScore4": 0, "playerScore5": 0, "playerScore6": 0, "playerScore7": 0, "playerScore8": 0, "playerScore9": 0, "playerSubteamId": 0, "profileIcon": 23, "pushPings": 4, "puuid": "NHNmXsPqDG4Uvq9NX87StQTfR5oBEqb5hf-E7yx29CQZgSNpYKZuPdYh4ufzZ1nsYWTvckOUaW7KFw", "quadraKills": 0, "riotIdName": "", "riotIdTagline": "", "role": "CARRY", "sightWardsBoughtInGame": 0, "spell1Casts": 16, "spell2Casts": 70, "spell3Casts": 10, "spell4Casts": 8, "subteamPlacement": 0, "summoner1Casts": 4, "summoner1Id": 4, "summoner2Casts": 4, "summoner2Id": 6, "summonerId": "PLGWjs5RbawAas4DJE_zyA5aQdi5NegkcEq_c0UTAXyIIdk", "summonerLevel": 87, "summonerName": "\uc601 \ub0b4", "teamEarlySurrendered": false, "teamId": 200, "teamPosition": "BOTTOM", "timeCCingOthers": 19, "timePlayed": 1707, "totalAllyJungleMinionsKilled": 0, "totalDamageDealt": 92242, "totalDamageDealtToChampions": 5326, "totalDamageShieldedOnTeammates": 0, "totalDamageTaken": 15245, "totalEnemyJungleMinionsKilled": 0, "totalHeal": 2710, "totalHealsOnTeammates": 0, "totalMinionsKilled": 161, "totalTimeCCDealt": 539, "totalTimeSpentDead": 55, "totalUnitsHealed": 1, "tripleKills": 0, "trueDamageDealt": 2605, "trueDamageDealtToChampions": 0, "trueDamageTaken": 463, "turretKills": 0, "turretTakedowns": 0, "turretsLost": 9, "unrealKills": 0, "visionClearedPings": 0, "visionScore": 20, "visionWardsBoughtInGame": 0, "wardsKilled": 2, "wardsPlaced": 9, "win": false}, {"allInPings": 3, "assistMePings": 11, "assists": 9, "baitPings": 0, "baronKills": 0, "basicPings": 0, "bountyLevel": 0, "challenges": {"12AssistStreakCount": 0, "abilityUses": 251, "acesBefore15Minutes": 0, "alliedJungleMonsterKills": 14, "baronTakedowns": 0, "blastConeOppositeOpponentCount": 0, "bountyGold": 150, "buffsStolen": 0, "completeSupportQuestInTime": 1, "controlWardTimeCoverageInRiverOrEnemyHalf": 0.7712115836583765, "controlWardsPlaced": 6, "damagePerMinute": 607.8979443581852, "damageTakenOnTeamPercentage": 0.10404422808429131, "dancedWithRiftHerald": 0, "deathsByEnemyChamps": 6, "dodgeSkillShotsSmallWindow": 0, "doubleAces": 0, "dragonTakedowns": 2, "earliestDragonTakedown": 388.63081589999996, "earlyLaningPhaseGoldExpAdvantage": 0, "effectiveHealAndShielding": 1112.2618408203125, "elderDragonKillsWithOpposingSoul": 0, "elderDragonMultikills": 0, "enemyChampionImmobilizations": 18, "enemyJungleMonsterKills": 0, "epicMonsterKillsNearEnemyJungler": 0, "epicMonsterKillsWithin30SecondsOfSpawn": 0, "epicMonsterSteals": 0, "epicMonsterStolenWithoutSmite": 0, "firstTurretKilled": 0, "flawlessAces": 0, "fullTeamTakedown": 0, "gameLength": 1707.9645269999999, "getTakedownsInAllLanesEarlyJungleAsLaner": 0, "goldPerMinute": 285.811960222945, "hadOpenNexus": 0, "immobilizeAndKillWithAlly": 3, "initialBuffCount": 0, "initialCrabCount": 0, "jungleCsBefore10Minutes": 0, "junglerTakedownsNearDamagedEpicMonster": 0, "kTurretsDestroyedBeforePlatesFall": 0, "kda": 1.8333333333333333, "killAfterHiddenWithAlly": 2, "killParticipation": 0.4782608695652174, "killedChampTookFullTeamDamageSurvived": 0, "killingSprees": 0, "killsNearEnemyTurret": 0, "killsOnOtherLanesEarlyJungleAsLaner": 0, "killsOnRecentlyHealedByAramPack": 0, "killsUnderOwnTurret": 0, "killsWithHelpFromEpicMonster": 0, "knockEnemyIntoTeamAndKill": 0, "landSkillShotsEarlyGame": 7, "laneMinionsFirst10Minutes": 6, "laningPhaseGoldExpAdvantage": 0, "legendaryCount": 0, "lostAnInhibitor": 0, "maxCsAdvantageOnLaneOpponent": 4, "maxKillDeficit": 0, "maxLevelLeadLaneOpponent": 1, "mejaisFullStackInTime": 0, "moreEnemyJungleThanOpponent": 0, "multiKillOneSpell": 0, "multiTurretRiftHeraldCount": 0, "multikills": 0, "multikillsAfterAggressiveFlash": 0, "mythicItemUsed": 6655, "outerTurretExecutesBefore10Minutes": 0, "outnumberedKills": 0, "outnumberedNexusKill": 0, "perfectDragonSoulsTaken": 0, "perfectGame": 0, "pickKillWithAlly": 10, "playedChampSelectPosition": 1, "poroExplosions": 0, "quickCleanse": 0, "quickFirstTurret": 0, "quickSoloKills": 0, "riftHeraldTakedowns": 0, "saveAllyFromDeath": 0, "scuttleCrabKills": 0, "skillshotsDodged": 11, "skillshotsHit": 19, "snowballsHit": 0, "soloBaronKills": 0, "soloKills": 1, "stealthWardsPlaced": 16, "survivedSingleDigitHpCount": 0, "survivedThreeImmobilizesInFight": 0, "takedownOnFirstTurret": 0, "takedowns": 11, "takedownsAfterGainingLevelAdvantage": 0, "takedownsBeforeJungleMinionSpawn": 0, "takedownsFirstXMinutes": 8, "takedownsInAlcove": 0, "takedownsInEnemyFountain": 0, "teamBaronKills": 0, "teamDamagePercentage": 0.2121367215228396, "teamElderDragonKills": 0, "teamRiftHeraldKills": 0, "tookLargeDamageSurvived": 0, "turretPlatesTaken": 1, "turretTakedowns": 0, "turretsTakenWithRiftHerald": 0, "twentyMinionsIn3SecondsCount": 0, "twoWardsOneSweeperCount": 1, "unseenRecalls": 0, "visionScoreAdvantageLaneOpponent": -0.31414520740509033, "visionScorePerMinute": 1.8213012488551472, "wardTakedowns": 6, "wardTakedownsBefore20M": 3, "wardsGuarded": 0}, "champExperience": 8613, "champLevel": 12, "championId": 99, "championName": "Lux", "championTransform": 0, "commandPings": 4, "consumablesPurchased": 8, "damageDealtToBuildings": 743, "damageDealtToObjectives": 4628, "damageDealtToTurrets": 743, "damageSelfMitigated": 8956, "dangerPings": 0, "deaths": 6, "detectorWardsPlaced": 6, "doubleKills": 0, "dragonKills": 0, "eligibleForProgression": true, "enemyMissingPings": 23, "enemyVisionPings": 12, "firstBloodAssist": false, "firstBloodKill": false, "firstTowerAssist": false, "firstTowerKill": false, "gameEndedInEarlySurrender": false, "gameEndedInSurrender": false, "getBackPings": 0, "goldEarned": 8135, "goldSpent": 7200, "holdPings": 0, "individualPosition": "UTILITY", "inhibitorKills": 0, "inhibitorTakedowns": 0, "inhibitorsLost": 1, "item0": 3853, "item1": 6655, "item2": 3145, "item3": 3020, "item4": 3108, "item5": 0, "item6": 3364, "itemsPurchased": 20, "killingSprees": 1, "kills": 2, "lane": "BOTTOM", "largestCriticalStrike": 0, "largestKillingSpree": 2, "largestMultiKill": 1, "longestTimeSpentLiving": 796, "magicDamageDealt": 68652, "magicDamageDealtToChampions": 15477, "magicDamageTaken": 4465, "missions": {"playerScore0": 0, "playerScore1": 0, "playerScore10": 0, "playerScore11": 0, "playerScore2": 0, "playerScore3": 0, "playerScore4": 0, "playerScore5": 0, "playerScore6": 0, "playerScore7": 0, "playerScore8": 0, "playerScore9": 0}, "needVisionPings": 1, "neutralMinionsKilled": 12, "nexusKills": 0, "nexusLost": 1, "nexusTakedowns": 0, "objectivesStolen": 0, "objectivesStolenAssists": 0, "onMyWayPings": 14, "participantId": 10, "pentaKills": 0, "perks": {"statPerks": {"defense": 5002, "flex": 5008, "offense": 5008}, "styles": [{"description": "primaryStyle", "selections": [{"perk": 8229, "var1": 1475, "var2": 0, "var3": 0}, {"perk": 8226, "var1": 250, "var2": 505, "var3": 0}, {"perk": 8210, "var1": 1, "var2": 0, "var3": 0}, {"perk": 8236, "var1": 24, "var2": 0, "var3": 0}], "style": 8200}, {"description": "subStyle", "selections": [{"perk": 8126, "var1": 825, "var2": 0, "var3": 0}, {"perk": 8106, "var1": 4, "var2": 0, "var3": 0}], "style": 8100}]}, "physicalDamageDealt": 7461, "physicalDamageDealtToChampions": 572, "physicalDamageTaken": 8413, "placement": 0, "playerAugment1": 0, "playerAugment2": 0, "playerAugment3": 0, "playerAugment4": 0, "playerScore0": 0, "playerScore1": 0, "playerScore10": 0, "playerScore11": 0, "playerScore2": 0, "playerScore3": 0, "playerScore4": 0, "playerScore5": 0, "playerScore6": 0, "playerScore7": 0, "playerScore8": 0, "playerScore9": 0, "playerSubteamId": 0, "profileIcon": 5799, "pushPings": 0, "puuid": "hSFj7234LwYnykejPCdj_qggqmlUtktq91j8eXzEvOAtgnM0Tx8wHskMz40Vc5KWt8zjjRlOEuJ9YQ", "quadraKills": 0, "riotIdName": "", "riotIdTagline": "", "role": "SUPPORT", "sightWardsBoughtInGame": 0, "spell1Casts": 57, "spell2Casts": 22, "spell3Casts": 156, "spell4Casts": 16, "subteamPlacement": 0, "summoner1Casts": 4, "summoner1Id": 14, "summoner2Casts": 2, "summoner2Id": 4, "summonerId": "Bp4Zc50d4vWxY2rFQgK0KkCHZwQQRiAzmBWMneJ3NvrSYVo", "summonerLevel": 209, "summonerName": "HKitty", "teamEarlySurrendered": false, "teamId": 200, "teamPosition": "UTILITY", "timeCCingOthers": 37, "timePlayed": 1707, "totalAllyJungleMinionsKilled": 10, "totalDamageDealt": 77726, "totalDamageDealtToChampions": 17304, "totalDamageShieldedOnTeammates": 1112, "totalDamageTaken": 13342, "totalEnemyJungleMinionsKilled": 0, "totalHeal": 1932, "totalHealsOnTeammates": 0, "totalMinionsKilled": 33, "totalTimeCCDealt": 343, "totalTimeSpentDead": 92, "totalUnitsHealed": 1, "tripleKills": 0, "trueDamageDealt": 1612, "trueDamageDealtToChampions": 1254, "trueDamageTaken": 463, "turretKills": 0, "turretTakedowns": 0, "turretsLost": 9, "unrealKills": 0, "visionClearedPings": 0, "visionScore": 51, "visionWardsBoughtInGame": 6, "wardsKilled": 6, "wardsPlaced": 22, "win": false}], "platformId": "KR", "queueId": 420, "teams": [{"bans": [{"championId": 54, "pickTurn": 1}, {"championId": 7, "pickTurn": 2}, {"championId": 222, "pickTurn": 3}, {"championId": 126, "pickTurn": 4}, {"championId": 517, "pickTurn": 5}], "objectives": {"baron": {"first": true, "kills": 1}, "champion": {"first": true, "kills": 35}, "dragon": {"first": false, "kills": 2}, "horde": {"first": false, "kills": 0}, "inhibitor": {"first": true, "kills": 1}, "riftHerald": {"first": true, "kills": 2}, "tower": {"first": true, "kills": 9}}, "teamId": 100, "win": true}, {"bans": [{"championId": 350, "pickTurn": 6}, {"championId": 24, "pickTurn": 7}, {"championId": 61, "pickTurn": 8}, {"championId": 7, "pickTurn": 9}, {"championId": 56, "pickTurn": 10}], "objectives": {"baron": {"first": false, "kills": 0}, "champion": {"first": false, "kills": 23}, "dragon": {"first": true, "kills": 2}, "horde": {"first": false, "kills": 0}, "inhibitor": {"first": false, "kills": 1}, "riftHerald": {"first": false, "kills": 0}, "tower": {"first": false, "kills": 6}}, "teamId": 200, "win": false}], "tournamentCode": ""}}