{"metadata": {"dataVersion": "2", "matchId": "KR_6791543849", "participants": ["h8CCjElxH2N38BRd4kRvG2oC6sVQP6o1nj_IUIz9v_zHsnVfSN2-7P_6nvo66iXTrptMk8AtK-LqWA", "rIl7eTJ6ZQzxY4NAw-5MfJlDPqT-DAMSEtG2CG5qYL0KCHI2fgKl7mAj4xuGCAlRiLGWSLoAXIpowQ", "6D6km5WsL1qpgw73CBZmzUq0GsIQk5rEZFGVzGw7e4drP5VsFnTy5ELIARm_FOo6AJvqQtSqo_qHBQ", "kBVdyihy_WlhD6Kcvu9e9JmIOfDBHNyiaI3UjajOkUbzqYEsTAyMBlDDnjjqC014CnrdR_0_kp6Bjw", "OEYoN1cDClAhcIpQidBjQK3S8GQalS9ortO3FcOz93fjt14LacUkXDHglYzz0RdzeHhv7yYt9ZcmiQ", "4DFcT0Oe5vG4RiempGzpAZrumxrkWMqbUQO8APQeYQkaqc8Aq17xtYIKjTmoCm0BGtrpawkAEgMEyA", "eTqwVzqEpeTX4VWN_vQ5VkU1JiY0Ku5Ltiikv4EqFprCbbmR0UM0RY87XFC901xo97Ona1qmQZC27g", "417JybcWTqo0tlsto42SFnhEFWvVlywYXwql41jjwzL1EqwkjnfU_Aj_97-WJEDE8H0aug753Zn58w", "jDmpMChlWbsg8jjtAPRggqCD_6wM5QuVYEm1paDLCxzoUctYJWruEiDECPyg_siAmakJ8Lerqt6yJw", "IG86ORX03RQCSUqgrHKs4MQfpRfGSxYIy6VO_ImiQ2c0BOZCdKsxaWZfbp9z2_KgIuJtg_-obrmszw"]}, "info": {"gameCreation": 1699663299813, "gameDuration": 1860, "gameEndTimestamp": 1699665183742, "gameId": 6791543849, "gameMode": "CLASSIC", "gameName": "teambuilder-match-6791543849", "gameStartTimestamp": 1699663323156, "gameType": "MATCHED_GAME", "gameVersion": "13.22.541.9804", "mapId": 11, "participants": [{"allInPings": 0, "assistMePings": 0, "assists": 3, "baitPings": 0, "baronKills": 0, "basicPings": 0, "bountyLevel": 0, "challenges": {"12AssistStreakCount": 0, "abilityUses": 316, "acesBefore15Minutes": 0, "alliedJungleMonsterKills": 0, "baronTakedowns": 0, "blastConeOppositeOpponentCount": 0, "bountyGold": 0, "buffsStolen": 0, "completeSupportQuestInTime": 0, "controlWardTimeCoverageInRiverOrEnemyHalf": 0.5194249902914205, "controlWardsPlaced": 2, "damagePerMinute": 1008.5531926241113, "damageTakenOnTeamPercentage": 0.22607863503338219, "dancedWithRiftHerald": 0, "deathsByEnemyChamps": 7, "dodgeSkillShotsSmallWindow": 0, "doubleAces": 0, "dragonTakedowns": 0, "earlyLaningPhaseGoldExpAdvantage": 0, "effectiveHealAndShielding": 0, "elderDragonKillsWithOpposingSoul": 0, "elderDragonMultikills": 0, "enemyChampionImmobilizations": 0, "enemyJungleMonsterKills": 1, "epicMonsterKillsNearEnemyJungler": 0, "epicMonsterKillsWithin30SecondsOfSpawn": 0, "epicMonsterSteals": 0, "epicMonsterStolenWithoutSmite": 0, "firstTurretKilled": 0, "flawlessAces": 0, "fullTeamTakedown": 1, "gameLength": 1860.8363302999999, "getTakedownsInAllLanesEarlyJungleAsLaner": 0, "goldPerMinute": 458.42460735113264, "hadOpenNexus": 0, "immobilizeAndKillWithAlly": 0, "initialBuffCount": 0, "initialCrabCount": 0, "jungleCsBefore10Minutes": 0, "junglerTakedownsNearDamagedEpicMonster": 0, "kTurretsDestroyedBeforePlatesFall": 0, "kda": 1.8571428571428572, "killAfterHiddenWithAlly": 2, "killParticipation": 0.41935483870967744, "killedChampTookFullTeamDamageSurvived": 0, "killingSprees": 1, "killsNearEnemyTurret": 2, "killsOnOtherLanesEarlyJungleAsLaner": 0, "killsOnRecentlyHealedByAramPack": 0, "killsUnderOwnTurret": 0, "killsWithHelpFromEpicMonster": 0, "knockEnemyIntoTeamAndKill": 0, "landSkillShotsEarlyGame": 12, "laneMinionsFirst10Minutes": 77, "laningPhaseGoldExpAdvantage": 1, "legendaryCount": 0, "lostAnInhibitor": 0, "maxCsAdvantageOnLaneOpponent": 92, "maxKillDeficit": 0, "maxLevelLeadLaneOpponent": 4, "mejaisFullStackInTime": 0, "moreEnemyJungleThanOpponent": 0, "multiKillOneSpell": 0, "multiTurretRiftHeraldCount": 0, "multikills": 0, "multikillsAfterAggressiveFlash": 0, "mythicItemUsed": 6692, "outerTurretExecutesBefore10Minutes": 0, "outnumberedKills": 0, "outnumberedNexusKill": 0, "perfectDragonSoulsTaken": 0, "perfectGame": 0, "pickKillWithAlly": 9, "playedChampSelectPosition": 1, "poroExplosions": 0, "quickCleanse": 0, "quickFirstTurret": 0, "quickSoloKills": 0, "riftHeraldTakedowns": 0, "saveAllyFromDeath": 0, "scuttleCrabKills": 0, "skillshotsDodged": 17, "skillshotsHit": 71, "snowballsHit": 0, "soloBaronKills": 0, "soloKills": 4, "stealthWardsPlaced": 10, "survivedSingleDigitHpCount": 0, "survivedThreeImmobilizesInFight": 2, "takedownOnFirstTurret": 0, "takedowns": 13, "takedownsAfterGainingLevelAdvantage": 0, "takedownsBeforeJungleMinionSpawn": 0, "takedownsFirstXMinutes": 7, "takedownsInAlcove": 2, "takedownsInEnemyFountain": 0, "teamBaronKills": 0, "teamDamagePercentage": 0.33827237055579273, "teamElderDragonKills": 0, "teamRiftHeraldKills": 1, "tookLargeDamageSurvived": 0, "turretPlatesTaken": 3, "turretTakedowns": 0, "turretsTakenWithRiftHerald": 0, "twentyMinionsIn3SecondsCount": 0, "twoWardsOneSweeperCount": 0, "unseenRecalls": 0, "visionScoreAdvantageLaneOpponent": -0.14068764448165894, "visionScorePerMinute": 0.9585273567311217, "wardTakedowns": 1, "wardTakedownsBefore20M": 0, "wardsGuarded": 1}, "champExperience": 16153, "champLevel": 16, "championId": 238, "championName": "Zed", "championTransform": 0, "commandPings": 18, "consumablesPurchased": 3, "damageDealtToBuildings": 1748, "damageDealtToObjectives": 1748, "damageDealtToTurrets": 1748, "damageSelfMitigated": 25758, "dangerPings": 0, "deaths": 7, "detectorWardsPlaced": 2, "doubleKills": 0, "dragonKills": 0, "eligibleForProgression": true, "enemyMissingPings": 8, "enemyVisionPings": 1, "firstBloodAssist": false, "firstBloodKill": false, "firstTowerAssist": false, "firstTowerKill": false, "gameEndedInEarlySurrender": false, "gameEndedInSurrender": true, "getBackPings": 5, "goldEarned": 14217, "goldSpent": 13900, "holdPings": 0, "individualPosition": "TOP", "inhibitorKills": 0, "inhibitorTakedowns": 0, "inhibitorsLost": 2, "item0": 3158, "item1": 3074, "item2": 6692, "item3": 3071, "item4": 6676, "item5": 0, "item6": 3340, "itemsPurchased": 23, "killingSprees": 2, "kills": 10, "lane": "TOP", "largestCriticalStrike": 0, "largestKillingSpree": 7, "largestMultiKill": 1, "longestTimeSpentLiving": 723, "magicDamageDealt": 7694, "magicDamageDealtToChampions": 1477, "magicDamageTaken": 6400, "missions": {"playerScore0": 0, "playerScore1": 0, "playerScore10": 0, "playerScore11": 0, "playerScore2": 0, "playerScore3": 0, "playerScore4": 0, "playerScore5": 0, "playerScore6": 0, "playerScore7": 0, "playerScore8": 0, "playerScore9": 0}, "needVisionPings": 0, "neutralMinionsKilled": 4, "nexusKills": 0, "nexusLost": 0, "nexusTakedowns": 0, "objectivesStolen": 0, "objectivesStolenAssists": 0, "onMyWayPings": 5, "participantId": 1, "pentaKills": 0, "perks": {"statPerks": {"defense": 5003, "flex": 5008, "offense": 5008}, "styles": [{"description": "primaryStyle", "selections": [{"perk": 8369, "var1": 1058, "var2": 1188, "var3": 0}, {"perk": 8304, "var1": 9, "var2": 4, "var3": 5}, {"perk": 8321, "var1": 5, "var2": 0, "var3": 0}, {"perk": 8347, "var1": 0, "var2": 0, "var3": 0}], "style": 8300}, {"description": "subStyle", "selections": [{"perk": 8237, "var1": 730, "var2": 0, "var3": 0}, {"perk": 8210, "var1": 6, "var2": 0, "var3": 0}], "style": 8200}]}, "physicalDamageDealt": 166168, "physicalDamageDealtToChampions": 28910, "physicalDamageTaken": 21647, "placement": 0, "playerAugment1": 0, "playerAugment2": 0, "playerAugment3": 0, "playerAugment4": 0, "playerScore0": 0, "playerScore1": 0, "playerScore10": 0, "playerScore11": 0, "playerScore2": 0, "playerScore3": 0, "playerScore4": 0, "playerScore5": 0, "playerScore6": 0, "playerScore7": 0, "playerScore8": 0, "playerScore9": 0, "playerSubteamId": 0, "profileIcon": 3545, "pushPings": 0, "puuid": "h8CCjElxH2N38BRd4kRvG2oC6sVQP6o1nj_IUIz9v_zHsnVfSN2-7P_6nvo66iXTrptMk8AtK-LqWA", "quadraKills": 0, "riotIdName": "", "riotIdTagline": "", "role": "SOLO", "sightWardsBoughtInGame": 0, "spell1Casts": 101, "spell2Casts": 86, "spell3Casts": 109, "spell4Casts": 20, "subteamPlacement": 0, "summoner1Casts": 3, "summoner1Id": 12, "summoner2Casts": 4, "summoner2Id": 4, "summonerId": "Egu5AU6C6-KDS4VXF1XHvMXC0Lw9Vypv2EOh-d3I3THNJ24", "summonerLevel": 99, "summonerName": "3star master i", "teamEarlySurrendered": false, "teamId": 100, "teamPosition": "TOP", "timeCCingOthers": 8, "timePlayed": 1860, "totalAllyJungleMinionsKilled": 0, "totalDamageDealt": 182235, "totalDamageDealtToChampions": 31279, "totalDamageShieldedOnTeammates": 0, "totalDamageTaken": 29320, "totalEnemyJungleMinionsKilled": 4, "totalHeal": 6321, "totalHealsOnTeammates": 0, "totalMinionsKilled": 233, "totalTimeCCDealt": 145, "totalTimeSpentDead": 223, "totalUnitsHealed": 1, "tripleKills": 0, "trueDamageDealt": 8372, "trueDamageDealtToChampions": 891, "trueDamageTaken": 1272, "turretKills": 0, "turretTakedowns": 0, "turretsLost": 10, "unrealKills": 0, "visionClearedPings": 0, "visionScore": 29, "visionWardsBoughtInGame": 2, "wardsKilled": 1, "wardsPlaced": 12, "win": false}, {"allInPings": 0, "assistMePings": 6, "assists": 8, "baitPings": 0, "baronKills": 0, "basicPings": 0, "bountyLevel": 0, "challenges": {"12AssistStreakCount": 0, "abilityUses": 264, "acesBefore15Minutes": 0, "alliedJungleMonsterKills": 48, "baronTakedowns": 0, "blastConeOppositeOpponentCount": 0, "bountyGold": 800, "buffsStolen": 0, "completeSupportQuestInTime": 0, "controlWardTimeCoverageInRiverOrEnemyHalf": 0.8000683409163554, "controlWardsPlaced": 8, "damagePerMinute": 602.5240030146783, "damageTakenOnTeamPercentage": 0.2432233354883821, "dancedWithRiftHerald": 0, "deathsByEnemyChamps": 7, "dodgeSkillShotsSmallWindow": 0, "doubleAces": 0, "dragonTakedowns": 1, "earliestDragonTakedown": 810.090962, "earlyLaningPhaseGoldExpAdvantage": 0, "effectiveHealAndShielding": 0, "elderDragonKillsWithOpposingSoul": 0, "elderDragonMultikills": 0, "enemyChampionImmobilizations": 31, "enemyJungleMonsterKills": 2, "epicMonsterKillsNearEnemyJungler": 1, "epicMonsterKillsWithin30SecondsOfSpawn": 0, "epicMonsterSteals": 0, "epicMonsterStolenWithoutSmite": 0, "firstTurretKilled": 0, "flawlessAces": 0, "fullTeamTakedown": 1, "gameLength": 1860.8363302999999, "goldPerMinute": 392.1990296735771, "hadOpenNexus": 0, "immobilizeAndKillWithAlly": 13, "initialBuffCount": 1, "initialCrabCount": 2, "jungleCsBefore10Minutes": 44.00000008940697, "junglerKillsEarlyJungle": 0, "junglerTakedownsNearDamagedEpicMonster": 0, "kTurretsDestroyedBeforePlatesFall": 0, "kda": 2.2857142857142856, "killAfterHiddenWithAlly": 1, "killParticipation": 0.5161290322580645, "killedChampTookFullTeamDamageSurvived": 0, "killingSprees": 1, "killsNearEnemyTurret": 1, "killsOnLanersEarlyJungleAsJungler": 1, "killsOnRecentlyHealedByAramPack": 0, "killsUnderOwnTurret": 0, "killsWithHelpFromEpicMonster": 0, "knockEnemyIntoTeamAndKill": 0, "landSkillShotsEarlyGame": 0, "laneMinionsFirst10Minutes": 0, "laningPhaseGoldExpAdvantage": 0, "legendaryCount": 0, "lostAnInhibitor": 0, "maxCsAdvantageOnLaneOpponent": 0.4000000059604645, "maxKillDeficit": 0, "maxLevelLeadLaneOpponent": 0, "mejaisFullStackInTime": 0, "moreEnemyJungleThanOpponent": -51.50000008940697, "multiKillOneSpell": 0, "multiTurretRiftHeraldCount": 0, "multikills": 0, "multikillsAfterAggressiveFlash": 0, "mythicItemUsed": 6631, "outerTurretExecutesBefore10Minutes": 0, "outnumberedKills": 0, "outnumberedNexusKill": 0, "perfectDragonSoulsTaken": 0, "perfectGame": 0, "pickKillWithAlly": 15, "playedChampSelectPosition": 1, "poroExplosions": 0, "quickCleanse": 0, "quickFirstTurret": 0, "quickSoloKills": 0, "riftHeraldTakedowns": 1, "saveAllyFromDeath": 0, "scuttleCrabKills": 4, "skillshotsDodged": 12, "skillshotsHit": 5, "snowballsHit": 0, "soloBaronKills": 0, "soloKills": 0, "stealthWardsPlaced": 1, "survivedSingleDigitHpCount": 0, "survivedThreeImmobilizesInFight": 4, "takedownOnFirstTurret": 0, "takedowns": 16, "takedownsAfterGainingLevelAdvantage": 0, "takedownsBeforeJungleMinionSpawn": 0, "takedownsFirstXMinutes": 5, "takedownsInAlcove": 0, "takedownsInEnemyFountain": 0, "teamBaronKills": 0, "teamDamagePercentage": 0.20208871907513132, "teamElderDragonKills": 0, "teamRiftHeraldKills": 1, "tookLargeDamageSurvived": 0, "turretPlatesTaken": 1, "turretTakedowns": 0, "turretsTakenWithRiftHerald": 0, "twentyMinionsIn3SecondsCount": 0, "twoWardsOneSweeperCount": 1, "unseenRecalls": 0, "visionScoreAdvantageLaneOpponent": 1.2049777507781982, "visionScorePerMinute": 1.3489727975846966, "wardTakedowns": 6, "wardTakedownsBefore20M": 3, "wardsGuarded": 0}, "champExperience": 11292, "champLevel": 13, "championId": 80, "championName": "Pantheon", "championTransform": 0, "commandPings": 6, "consumablesPurchased": 9, "damageDealtToBuildings": 0, "damageDealtToObjectives": 21644, "damageDealtToTurrets": 0, "damageSelfMitigated": 27955, "dangerPings": 0, "deaths": 7, "detectorWardsPlaced": 8, "doubleKills": 0, "dragonKills": 1, "eligibleForProgression": true, "enemyMissingPings": 6, "enemyVisionPings": 6, "firstBloodAssist": false, "firstBloodKill": false, "firstTowerAssist": false, "firstTowerKill": false, "gameEndedInEarlySurrender": false, "gameEndedInSurrender": true, "getBackPings": 0, "goldEarned": 12163, "goldSpent": 11450, "holdPings": 0, "individualPosition": "JUNGLE", "inhibitorKills": 0, "inhibitorTakedowns": 0, "inhibitorsLost": 2, "item0": 0, "item1": 6631, "item2": 3071, "item3": 3047, "item4": 1036, "item5": 6609, "item6": 3364, "itemsPurchased": 30, "killingSprees": 1, "kills": 8, "lane": "JUNGLE", "largestCriticalStrike": 0, "largestKillingSpree": 3, "largestMultiKill": 1, "longestTimeSpentLiving": 495, "magicDamageDealt": 1164, "magicDamageDealtToChampions": 398, "magicDamageTaken": 5276, "missions": {"playerScore0": 0, "playerScore1": 0, "playerScore10": 0, "playerScore11": 0, "playerScore2": 0, "playerScore3": 0, "playerScore4": 0, "playerScore5": 0, "playerScore6": 0, "playerScore7": 0, "playerScore8": 0, "playerScore9": 0}, "needVisionPings": 0, "neutralMinionsKilled": 115, "nexusKills": 0, "nexusLost": 0, "nexusTakedowns": 0, "objectivesStolen": 0, "objectivesStolenAssists": 0, "onMyWayPings": 22, "participantId": 2, "pentaKills": 0, "perks": {"statPerks": {"defense": 5002, "flex": 5008, "offense": 5005}, "styles": [{"description": "primaryStyle", "selections": [{"perk": 8010, "var1": 581, "var2": 0, "var3": 0}, {"perk": 9111, "var1": 918, "var2": 320, "var3": 0}, {"perk": 9105, "var1": 13, "var2": 50, "var3": 0}, {"perk": 8014, "var1": 501, "var2": 0, "var3": 0}], "style": 8000}, {"description": "subStyle", "selections": [{"perk": 8347, "var1": 0, "var2": 0, "var3": 0}, {"perk": 8304, "var1": 9, "var2": 4, "var3": 5}], "style": 8300}]}, "physicalDamageDealt": 128187, "physicalDamageDealtToChampions": 17706, "physicalDamageTaken": 25110, "placement": 0, "playerAugment1": 0, "playerAugment2": 0, "playerAugment3": 0, "playerAugment4": 0, "playerScore0": 0, "playerScore1": 0, "playerScore10": 0, "playerScore11": 0, "playerScore2": 0, "playerScore3": 0, "playerScore4": 0, "playerScore5": 0, "playerScore6": 0, "playerScore7": 0, "playerScore8": 0, "playerScore9": 0, "playerSubteamId": 0, "profileIcon": 6296, "pushPings": 0, "puuid": "rIl7eTJ6ZQzxY4NAw-5MfJlDPqT-DAMSEtG2CG5qYL0KCHI2fgKl7mAj4xuGCAlRiLGWSLoAXIpowQ", "quadraKills": 0, "riotIdName": "", "riotIdTagline": "", "role": "NONE", "sightWardsBoughtInGame": 0, "spell1Casts": 164, "spell2Casts": 62, "spell3Casts": 32, "spell4Casts": 6, "subteamPlacement": 0, "summoner1Casts": 18, "summoner1Id": 11, "summoner2Casts": 6, "summoner2Id": 4, "summonerId": "wvQhFpH4Y9v33y5kegFmV0dx5z1ealm7vy6dPZjXDKAuF57vkSoPtedX8w", "summonerLevel": 44, "summonerName": "\ub9e4\uc2e4\ub18d\ucd95\uc561", "teamEarlySurrendered": false, "teamId": 100, "teamPosition": "JUNGLE", "timeCCingOthers": 45, "timePlayed": 1860, "totalAllyJungleMinionsKilled": 84, "totalDamageDealt": 161182, "totalDamageDealtToChampions": 18686, "totalDamageShieldedOnTeammates": 0, "totalDamageTaken": 31544, "totalEnemyJungleMinionsKilled": 2, "totalHeal": 10262, "totalHealsOnTeammates": 0, "totalMinionsKilled": 23, "totalTimeCCDealt": 358, "totalTimeSpentDead": 156, "totalUnitsHealed": 1, "tripleKills": 0, "trueDamageDealt": 31831, "trueDamageDealtToChampions": 581, "trueDamageTaken": 1157, "turretKills": 0, "turretTakedowns": 0, "turretsLost": 10, "unrealKills": 0, "visionClearedPings": 0, "visionScore": 41, "visionWardsBoughtInGame": 8, "wardsKilled": 6, "wardsPlaced": 9, "win": false}, {"allInPings": 0, "assistMePings": 0, "assists": 10, "baitPings": 0, "baronKills": 0, "basicPings": 0, "bountyLevel": 0, "challenges": {"12AssistStreakCount": 0, "abilityUses": 213, "acesBefore15Minutes": 0, "alliedJungleMonsterKills": 0, "baronTakedowns": 0, "blastConeOppositeOpponentCount": 0, "bountyGold": 150, "buffsStolen": 0, "completeSupportQuestInTime": 0, "controlWardTimeCoverageInRiverOrEnemyHalf": 0.6823047148350272, "controlWardsPlaced": 1, "damagePerMinute": 386.12133779944725, "damageTakenOnTeamPercentage": 0.21215822485426314, "dancedWithRiftHerald": 0, "deathsByEnemyChamps": 6, "dodgeSkillShotsSmallWindow": 0, "doubleAces": 0, "dragonTakedowns": 0, "earlyLaningPhaseGoldExpAdvantage": 0, "effectiveHealAndShielding": 621.4418334960938, "elderDragonKillsWithOpposingSoul": 0, "elderDragonMultikills": 0, "enemyChampionImmobilizations": 20, "enemyJungleMonsterKills": 0, "epicMonsterKillsNearEnemyJungler": 0, "epicMonsterKillsWithin30SecondsOfSpawn": 0, "epicMonsterSteals": 0, "epicMonsterStolenWithoutSmite": 0, "firstTurretKilled": 0, "flawlessAces": 0, "fullTeamTakedown": 1, "gameLength": 1860.8363302999999, "getTakedownsInAllLanesEarlyJungleAsLaner": 0, "goldPerMinute": 320.98168187833346, "hadOpenNexus": 0, "immobilizeAndKillWithAlly": 8, "initialBuffCount": 0, "initialCrabCount": 0, "jungleCsBefore10Minutes": 0, "junglerTakedownsNearDamagedEpicMonster": 0, "kTurretsDestroyedBeforePlatesFall": 0, "kda": 2.1666666666666665, "killAfterHiddenWithAlly": 2, "killParticipation": 0.41935483870967744, "killedChampTookFullTeamDamageSurvived": 0, "killingSprees": 0, "killsNearEnemyTurret": 1, "killsOnOtherLanesEarlyJungleAsLaner": 0, "killsOnRecentlyHealedByAramPack": 0, "killsUnderOwnTurret": 1, "killsWithHelpFromEpicMonster": 0, "knockEnemyIntoTeamAndKill": 8, "landSkillShotsEarlyGame": 0, "laneMinionsFirst10Minutes": 33, "laningPhaseGoldExpAdvantage": 0, "legendaryCount": 0, "lostAnInhibitor": 0, "maxCsAdvantageOnLaneOpponent": 0, "maxKillDeficit": 0, "maxLevelLeadLaneOpponent": 0, "mejaisFullStackInTime": 0, "moreEnemyJungleThanOpponent": 0, "multiKillOneSpell": 0, "multiTurretRiftHeraldCount": 0, "multikills": 0, "multikillsAfterAggressiveFlash": 0, "mythicItemUsed": 6667, "outerTurretExecutesBefore10Minutes": 0, "outnumberedKills": 0, "outnumberedNexusKill": 0, "perfectDragonSoulsTaken": 0, "perfectGame": 0, "pickKillWithAlly": 13, "playedChampSelectPosition": 1, "poroExplosions": 0, "quickCleanse": 0, "quickFirstTurret": 0, "quickSoloKills": 0, "riftHeraldTakedowns": 0, "saveAllyFromDeath": 0, "scuttleCrabKills": 0, "skillshotsDodged": 15, "skillshotsHit": 1, "snowballsHit": 0, "soloBaronKills": 0, "soloKills": 0, "stealthWardsPlaced": 0, "survivedSingleDigitHpCount": 0, "survivedThreeImmobilizesInFight": 4, "takedownOnFirstTurret": 0, "takedowns": 13, "takedownsAfterGainingLevelAdvantage": 0, "takedownsBeforeJungleMinionSpawn": 0, "takedownsFirstXMinutes": 7, "takedownsInAlcove": 0, "takedownsInEnemyFountain": 0, "teamBaronKills": 0, "teamDamagePercentage": 0.12950648633589032, "teamElderDragonKills": 0, "teamRiftHeraldKills": 1, "tookLargeDamageSurvived": 0, "turretPlatesTaken": 1, "turretTakedowns": 0, "turretsTakenWithRiftHerald": 0, "twentyMinionsIn3SecondsCount": 0, "twoWardsOneSweeperCount": 0, "unseenRecalls": 0, "visionScoreAdvantageLaneOpponent": -0.6721594333648682, "visionScorePerMinute": 0.33135659970585757, "wardTakedowns": 4, "wardTakedownsBefore20M": 4, "wardsGuarded": 0}, "champExperience": 12863, "champLevel": 14, "championId": 27, "championName": "Singed", "championTransform": 0, "commandPings": 1, "consumablesPurchased": 4, "damageDealtToBuildings": 63, "damageDealtToObjectives": 4774, "damageDealtToTurrets": 63, "damageSelfMitigated": 33445, "dangerPings": 0, "deaths": 6, "detectorWardsPlaced": 1, "doubleKills": 0, "dragonKills": 0, "eligibleForProgression": true, "enemyMissingPings": 7, "enemyVisionPings": 1, "firstBloodAssist": false, "firstBloodKill": false, "firstTowerAssist": false, "firstTowerKill": false, "gameEndedInEarlySurrender": false, "gameEndedInSurrender": true, "getBackPings": 12, "goldEarned": 9954, "goldSpent": 9900, "holdPings": 0, "individualPosition": "MIDDLE", "inhibitorKills": 0, "inhibitorTakedowns": 0, "inhibitorsLost": 2, "item0": 3047, "item1": 6667, "item2": 2031, "item3": 3116, "item4": 3143, "item5": 0, "item6": 3364, "itemsPurchased": 20, "killingSprees": 1, "kills": 3, "lane": "MIDDLE", "largestCriticalStrike": 0, "largestKillingSpree": 2, "largestMultiKill": 1, "longestTimeSpentLiving": 610, "magicDamageDealt": 109498, "magicDamageDealtToChampions": 10903, "magicDamageTaken": 3710, "missions": {"playerScore0": 0, "playerScore1": 0, "playerScore10": 0, "playerScore11": 0, "playerScore2": 0, "playerScore3": 0, "playerScore4": 0, "playerScore5": 0, "playerScore6": 0, "playerScore7": 0, "playerScore8": 0, "playerScore9": 0}, "needVisionPings": 0, "neutralMinionsKilled": 0, "nexusKills": 0, "nexusLost": 0, "nexusTakedowns": 0, "objectivesStolen": 0, "objectivesStolenAssists": 0, "onMyWayPings": 25, "participantId": 3, "pentaKills": 0, "perks": {"statPerks": {"defense": 5003, "flex": 5008, "offense": 5008}, "styles": [{"description": "primaryStyle", "selections": [{"perk": 8124, "var1": 680, "var2": 0, "var3": 0}, {"perk": 8126, "var1": 1057, "var2": 0, "var3": 0}, {"perk": 8138, "var1": 30, "var2": 0, "var3": 0}, {"perk": 8105, "var1": 13, "var2": 5, "var3": 0}], "style": 8100}, {"description": "subStyle", "selections": [{"perk": 8232, "var1": 4, "var2": 30, "var3": 0}, {"perk": 8234, "var1": 14612, "var2": 0, "var3": 0}], "style": 8200}]}, "physicalDamageDealt": 7091, "physicalDamageDealtToChampions": 337, "physicalDamageTaken": 22351, "placement": 0, "playerAugment1": 0, "playerAugment2": 0, "playerAugment3": 0, "playerAugment4": 0, "playerScore0": 0, "playerScore1": 0, "playerScore10": 0, "playerScore11": 0, "playerScore2": 0, "playerScore3": 0, "playerScore4": 0, "playerScore5": 0, "playerScore6": 0, "playerScore7": 0, "playerScore8": 0, "playerScore9": 0, "playerSubteamId": 0, "profileIcon": 5895, "pushPings": 0, "puuid": "6D6km5WsL1qpgw73CBZmzUq0GsIQk5rEZFGVzGw7e4drP5VsFnTy5ELIARm_FOo6AJvqQtSqo_qHBQ", "quadraKills": 0, "riotIdName": "", "riotIdTagline": "", "role": "SOLO", "sightWardsBoughtInGame": 0, "spell1Casts": 152, "spell2Casts": 24, "spell3Casts": 29, "spell4Casts": 8, "subteamPlacement": 0, "summoner1Casts": 4, "summoner1Id": 4, "summoner2Casts": 5, "summoner2Id": 6, "summonerId": "s5SbsJaxTgILa9YY49TzqNV5LOoeTd5-Bu8_H412ifIUNjM", "summonerLevel": 170, "summonerName": "\uae40\ub2f4\uc5f0", "teamEarlySurrendered": false, "teamId": 100, "teamPosition": "MIDDLE", "timeCCingOthers": 42, "timePlayed": 1860, "totalAllyJungleMinionsKilled": 0, "totalDamageDealt": 131184, "totalDamageDealtToChampions": 11975, "totalDamageShieldedOnTeammates": 0, "totalDamageTaken": 27515, "totalEnemyJungleMinionsKilled": 0, "totalHeal": 3533, "totalHealsOnTeammates": 621, "totalMinionsKilled": 168, "totalTimeCCDealt": 910, "totalTimeSpentDead": 140, "totalUnitsHealed": 4, "tripleKills": 0, "trueDamageDealt": 14593, "trueDamageDealtToChampions": 733, "trueDamageTaken": 1452, "turretKills": 0, "turretTakedowns": 0, "turretsLost": 10, "unrealKills": 0, "visionClearedPings": 0, "visionScore": 10, "visionWardsBoughtInGame": 2, "wardsKilled": 4, "wardsPlaced": 1, "win": false}, {"allInPings": 0, "assistMePings": 2, "assists": 8, "baitPings": 0, "baronKills": 0, "basicPings": 0, "bountyLevel": 0, "challenges": {"12AssistStreakCount": 0, "abilityUses": 300, "acesBefore15Minutes": 0, "alliedJungleMonsterKills": 20, "baronTakedowns": 0, "blastConeOppositeOpponentCount": 0, "bountyGold": 0, "buffsStolen": 0, "completeSupportQuestInTime": 0, "controlWardsPlaced": 0, "damagePerMinute": 667.3340125511199, "damageTakenOnTeamPercentage": 0.13541910728573642, "dancedWithRiftHerald": 0, "deathsByEnemyChamps": 5, "dodgeSkillShotsSmallWindow": 1, "doubleAces": 0, "dragonTakedowns": 0, "earlyLaningPhaseGoldExpAdvantage": 0, "effectiveHealAndShielding": 740.0816650390625, "elderDragonKillsWithOpposingSoul": 0, "elderDragonMultikills": 0, "enemyChampionImmobilizations": 5, "enemyJungleMonsterKills": 0, "epicMonsterKillsNearEnemyJungler": 0, "epicMonsterKillsWithin30SecondsOfSpawn": 0, "epicMonsterSteals": 0, "epicMonsterStolenWithoutSmite": 0, "firstTurretKilled": 0, "flawlessAces": 0, "fullTeamTakedown": 1, "gameLength": 1860.8363302999999, "getTakedownsInAllLanesEarlyJungleAsLaner": 0, "goldPerMinute": 426.45183640872085, "hadOpenNexus": 0, "immobilizeAndKillWithAlly": 0, "initialBuffCount": 0, "initialCrabCount": 0, "jungleCsBefore10Minutes": 0, "junglerTakedownsNearDamagedEpicMonster": 0, "kTurretsDestroyedBeforePlatesFall": 0, "kda": 3, "killAfterHiddenWithAlly": 4, "killParticipation": 0.4838709677419355, "killedChampTookFullTeamDamageSurvived": 0, "killingSprees": 1, "killsNearEnemyTurret": 2, "killsOnOtherLanesEarlyJungleAsLaner": 0, "killsOnRecentlyHealedByAramPack": 0, "killsUnderOwnTurret": 2, "killsWithHelpFromEpicMonster": 0, "knockEnemyIntoTeamAndKill": 0, "landSkillShotsEarlyGame": 0, "laneMinionsFirst10Minutes": 64, "laningPhaseGoldExpAdvantage": 0, "legendaryCount": 0, "lostAnInhibitor": 0, "maxCsAdvantageOnLaneOpponent": 0, "maxKillDeficit": 0, "maxLevelLeadLaneOpponent": 1, "mejaisFullStackInTime": 0, "moreEnemyJungleThanOpponent": 0, "multiKillOneSpell": 0, "multiTurretRiftHeraldCount": 0, "multikills": 0, "multikillsAfterAggressiveFlash": 0, "mythicItemUsed": 6671, "outerTurretExecutesBefore10Minutes": 0, "outnumberedKills": 0, "outnumberedNexusKill": 0, "perfectDragonSoulsTaken": 0, "perfectGame": 0, "pickKillWithAlly": 12, "playedChampSelectPosition": 1, "poroExplosions": 0, "quickCleanse": 0, "quickFirstTurret": 0, "quickSoloKills": 0, "riftHeraldTakedowns": 0, "saveAllyFromDeath": 0, "scuttleCrabKills": 0, "skillshotsDodged": 19, "skillshotsHit": 32, "snowballsHit": 0, "soloBaronKills": 0, "soloKills": 2, "soloTurretsLategame": 1, "stealthWardsPlaced": 9, "survivedSingleDigitHpCount": 0, "survivedThreeImmobilizesInFight": 0, "takedownOnFirstTurret": 0, "takedowns": 15, "takedownsAfterGainingLevelAdvantage": 0, "takedownsBeforeJungleMinionSpawn": 0, "takedownsFirstXMinutes": 7, "takedownsInAlcove": 1, "takedownsInEnemyFountain": 0, "teamBaronKills": 0, "teamDamagePercentage": 0.22382622952273992, "teamElderDragonKills": 0, "teamRiftHeraldKills": 1, "tookLargeDamageSurvived": 0, "turretPlatesTaken": 1, "turretTakedowns": 2, "turretsTakenWithRiftHerald": 0, "twentyMinionsIn3SecondsCount": 0, "twoWardsOneSweeperCount": 0, "unseenRecalls": 0, "visionScoreAdvantageLaneOpponent": -0.07796835899353027, "visionScorePerMinute": 0.7468618552423344, "wardTakedowns": 5, "wardTakedownsBefore20M": 4, "wardsGuarded": 0}, "champExperience": 13086, "champLevel": 15, "championId": 523, "championName": "Aphelios", "championTransform": 0, "commandPings": 10, "consumablesPurchased": 1, "damageDealtToBuildings": 4510, "damageDealtToObjectives": 4510, "damageDealtToTurrets": 4510, "damageSelfMitigated": 18955, "dangerPings": 0, "deaths": 5, "detectorWardsPlaced": 0, "doubleKills": 0, "dragonKills": 0, "eligibleForProgression": true, "enemyMissingPings": 2, "enemyVisionPings": 7, "firstBloodAssist": false, "firstBloodKill": true, "firstTowerAssist": false, "firstTowerKill": false, "gameEndedInEarlySurrender": false, "gameEndedInSurrender": true, "getBackPings": 8, "goldEarned": 13225, "goldSpent": 11550, "holdPings": 0, "individualPosition": "BOTTOM", "inhibitorKills": 0, "inhibitorTakedowns": 0, "inhibitorsLost": 2, "item0": 3006, "item1": 3095, "item2": 6671, "item3": 3072, "item4": 1055, "item5": 0, "item6": 3340, "itemsPurchased": 16, "killingSprees": 2, "kills": 7, "lane": "BOTTOM", "largestCriticalStrike": 616, "largestKillingSpree": 5, "largestMultiKill": 1, "longestTimeSpentLiving": 1004, "magicDamageDealt": 11822, "magicDamageDealtToChampions": 2094, "magicDamageTaken": 1584, "missions": {"playerScore0": 0, "playerScore1": 0, "playerScore10": 0, "playerScore11": 0, "playerScore2": 0, "playerScore3": 0, "playerScore4": 0, "playerScore5": 0, "playerScore6": 0, "playerScore7": 0, "playerScore8": 0, "playerScore9": 0}, "needVisionPings": 0, "neutralMinionsKilled": 15, "nexusKills": 0, "nexusLost": 0, "nexusTakedowns": 0, "objectivesStolen": 0, "objectivesStolenAssists": 0, "onMyWayPings": 25, "participantId": 4, "pentaKills": 0, "perks": {"statPerks": {"defense": 5002, "flex": 5008, "offense": 5005}, "styles": [{"description": "primaryStyle", "selections": [{"perk": 8021, "var1": 1203, "var2": 1183, "var3": 0}, {"perk": 9101, "var1": 5073, "var2": 5979, "var3": 0}, {"perk": 9103, "var1": 17, "var2": 50, "var3": 0}, {"perk": 8017, "var1": 659, "var2": 0, "var3": 0}], "style": 8000}, {"description": "subStyle", "selections": [{"perk": 8233, "var1": 19, "var2": 50, "var3": 0}, {"perk": 8236, "var1": 28, "var2": 0, "var3": 0}], "style": 8200}]}, "physicalDamageDealt": 188587, "physicalDamageDealtToChampions": 18552, "physicalDamageTaken": 15263, "placement": 0, "playerAugment1": 0, "playerAugment2": 0, "playerAugment3": 0, "playerAugment4": 0, "playerScore0": 0, "playerScore1": 0, "playerScore10": 0, "playerScore11": 0, "playerScore2": 0, "playerScore3": 0, "playerScore4": 0, "playerScore5": 0, "playerScore6": 0, "playerScore7": 0, "playerScore8": 0, "playerScore9": 0, "playerSubteamId": 0, "profileIcon": 5766, "pushPings": 0, "puuid": "kBVdyihy_WlhD6Kcvu9e9JmIOfDBHNyiaI3UjajOkUbzqYEsTAyMBlDDnjjqC014CnrdR_0_kp6Bjw", "quadraKills": 0, "riotIdName": "", "riotIdTagline": "", "role": "CARRY", "sightWardsBoughtInGame": 0, "spell1Casts": 64, "spell2Casts": 229, "spell3Casts": 0, "spell4Casts": 7, "subteamPlacement": 0, "summoner1Casts": 5, "summoner1Id": 7, "summoner2Casts": 4, "summoner2Id": 4, "summonerId": "U-9k7_jn8RxBrMVqxo66q_qq5d2TkySzUSpr-7kjdjPK5yCtzeAIg1jErw", "summonerLevel": 75, "summonerName": "0l\ubc29\uc6d0", "teamEarlySurrendered": false, "teamId": 100, "teamPosition": "BOTTOM", "timeCCingOthers": 8, "timePlayed": 1860, "totalAllyJungleMinionsKilled": 15, "totalDamageDealt": 205188, "totalDamageDealtToChampions": 20696, "totalDamageShieldedOnTeammates": 0, "totalDamageTaken": 17562, "totalEnemyJungleMinionsKilled": 0, "totalHeal": 5353, "totalHealsOnTeammates": 740, "totalMinionsKilled": 238, "totalTimeCCDealt": 169, "totalTimeSpentDead": 161, "totalUnitsHealed": 4, "tripleKills": 0, "trueDamageDealt": 4778, "trueDamageDealtToChampions": 50, "trueDamageTaken": 714, "turretKills": 2, "turretTakedowns": 2, "turretsLost": 10, "unrealKills": 0, "visionClearedPings": 0, "visionScore": 23, "visionWardsBoughtInGame": 0, "wardsKilled": 5, "wardsPlaced": 9, "win": false}, {"allInPings": 0, "assistMePings": 2, "assists": 15, "baitPings": 0, "baronKills": 0, "basicPings": 0, "bountyLevel": 0, "challenges": {"12AssistStreakCount": 1, "abilityUses": 107, "acesBefore15Minutes": 0, "alliedJungleMonsterKills": 0, "baronTakedowns": 0, "blastConeOppositeOpponentCount": 0, "bountyGold": 0, "buffsStolen": 0, "completeSupportQuestInTime": 0, "controlWardTimeCoverageInRiverOrEnemyHalf": 0.4898926967709364, "controlWardsPlaced": 11, "damagePerMinute": 316.9500710125135, "damageTakenOnTeamPercentage": 0.1831206973382362, "dancedWithRiftHerald": 0, "deathsByEnemyChamps": 6, "dodgeSkillShotsSmallWindow": 1, "doubleAces": 0, "dragonTakedowns": 0, "earlyLaningPhaseGoldExpAdvantage": 0, "effectiveHealAndShielding": 2520.087158203125, "elderDragonKillsWithOpposingSoul": 0, "elderDragonMultikills": 0, "enemyChampionImmobilizations": 57, "enemyJungleMonsterKills": 0, "epicMonsterKillsNearEnemyJungler": 0, "epicMonsterKillsWithin30SecondsOfSpawn": 0, "epicMonsterSteals": 0, "epicMonsterStolenWithoutSmite": 0, "firstTurretKilled": 0, "flawlessAces": 0, "fullTeamTakedown": 1, "gameLength": 1860.8363302999999, "getTakedownsInAllLanesEarlyJungleAsLaner": 0, "goldPerMinute": 257.516660449455, "hadOpenNexus": 0, "immobilizeAndKillWithAlly": 12, "initialBuffCount": 0, "initialCrabCount": 0, "jungleCsBefore10Minutes": 0, "junglerTakedownsNearDamagedEpicMonster": 0, "kTurretsDestroyedBeforePlatesFall": 0, "kda": 3, "killAfterHiddenWithAlly": 3, "killParticipation": 0.5806451612903226, "killedChampTookFullTeamDamageSurvived": 0, "killingSprees": 1, "killsNearEnemyTurret": 0, "killsOnOtherLanesEarlyJungleAsLaner": 0, "killsOnRecentlyHealedByAramPack": 0, "killsUnderOwnTurret": 1, "killsWithHelpFromEpicMonster": 0, "knockEnemyIntoTeamAndKill": 11, "landSkillShotsEarlyGame": 2, "laneMinionsFirst10Minutes": 15, "laningPhaseGoldExpAdvantage": 1, "legendaryCount": 0, "lostAnInhibitor": 0, "maxCsAdvantageOnLaneOpponent": 17, "maxKillDeficit": 0, "maxLevelLeadLaneOpponent": 2, "mejaisFullStackInTime": 0, "moreEnemyJungleThanOpponent": 0, "multiKillOneSpell": 0, "multiTurretRiftHeraldCount": 0, "multikills": 0, "multikillsAfterAggressiveFlash": 0, "mythicItemUsed": 3190, "outerTurretExecutesBefore10Minutes": 0, "outnumberedKills": 0, "outnumberedNexusKill": 0, "perfectDragonSoulsTaken": 0, "perfectGame": 0, "pickKillWithAlly": 17, "playedChampSelectPosition": 1, "poroExplosions": 0, "quickCleanse": 0, "quickFirstTurret": 0, "quickSoloKills": 0, "riftHeraldTakedowns": 0, "saveAllyFromDeath": 0, "scuttleCrabKills": 0, "skillshotsDodged": 27, "skillshotsHit": 18, "snowballsHit": 0, "soloBaronKills": 0, "soloKills": 0, "stealthWardsPlaced": 30, "survivedSingleDigitHpCount": 0, "survivedThreeImmobilizesInFight": 2, "takedownOnFirstTurret": 0, "takedowns": 18, "takedownsAfterGainingLevelAdvantage": 0, "takedownsBeforeJungleMinionSpawn": 0, "takedownsFirstXMinutes": 8, "takedownsInAlcove": 1, "takedownsInEnemyFountain": 0, "teamBaronKills": 0, "teamDamagePercentage": 0.1063061945104457, "teamElderDragonKills": 0, "teamRiftHeraldKills": 1, "tookLargeDamageSurvived": 0, "turretPlatesTaken": 0, "turretTakedowns": 0, "turretsTakenWithRiftHerald": 0, "twentyMinionsIn3SecondsCount": 0, "twoWardsOneSweeperCount": 0, "unseenRecalls": 0, "visionScoreAdvantageLaneOpponent": 0.11269283294677734, "visionScorePerMinute": 2.905228687931121, "wardTakedowns": 10, "wardTakedownsBefore20M": 6, "wardsGuarded": 2}, "champExperience": 9917, "champLevel": 12, "championId": 412, "championName": "Thresh", "championTransform": 0, "commandPings": 4, "consumablesPurchased": 14, "damageDealtToBuildings": 0, "damageDealtToObjectives": 0, "damageDealtToTurrets": 0, "damageSelfMitigated": 22433, "dangerPings": 0, "deaths": 6, "detectorWardsPlaced": 11, "doubleKills": 0, "dragonKills": 0, "eligibleForProgression": true, "enemyMissingPings": 2, "enemyVisionPings": 0, "firstBloodAssist": true, "firstBloodKill": false, "firstTowerAssist": false, "firstTowerKill": false, "gameEndedInEarlySurrender": false, "gameEndedInSurrender": true, "getBackPings": 0, "goldEarned": 7986, "goldSpent": 7300, "holdPings": 0, "individualPosition": "UTILITY", "inhibitorKills": 0, "inhibitorTakedowns": 0, "inhibitorsLost": 2, "item0": 3857, "item1": 3190, "item2": 2055, "item3": 3109, "item4": 3117, "item5": 1028, "item6": 3364, "itemsPurchased": 30, "killingSprees": 1, "kills": 3, "lane": "BOTTOM", "largestCriticalStrike": 0, "largestKillingSpree": 3, "largestMultiKill": 1, "longestTimeSpentLiving": 621, "magicDamageDealt": 11252, "magicDamageDealtToChampions": 6985, "magicDamageTaken": 3367, "missions": {"playerScore0": 0, "playerScore1": 0, "playerScore10": 0, "playerScore11": 0, "playerScore2": 0, "playerScore3": 0, "playerScore4": 0, "playerScore5": 0, "playerScore6": 0, "playerScore7": 0, "playerScore8": 0, "playerScore9": 0}, "needVisionPings": 0, "neutralMinionsKilled": 0, "nexusKills": 0, "nexusLost": 0, "nexusTakedowns": 0, "objectivesStolen": 0, "objectivesStolenAssists": 0, "onMyWayPings": 4, "participantId": 5, "pentaKills": 0, "perks": {"statPerks": {"defense": 5002, "flex": 5008, "offense": 5008}, "styles": [{"description": "primaryStyle", "selections": [{"perk": 8351, "var1": 77, "var2": 1294, "var3": 0}, {"perk": 8306, "var1": 3, "var2": 0, "var3": 0}, {"perk": 8345, "var1": 3, "var2": 0, "var3": 0}, {"perk": 8347, "var1": 0, "var2": 0, "var3": 0}], "style": 8300}, {"description": "subStyle", "selections": [{"perk": 8429, "var1": 61, "var2": 11, "var3": 11}, {"perk": 8451, "var1": 191, "var2": 0, "var3": 0}], "style": 8400}]}, "physicalDamageDealt": 4993, "physicalDamageDealtToChampions": 1583, "physicalDamageTaken": 18502, "placement": 0, "playerAugment1": 0, "playerAugment2": 0, "playerAugment3": 0, "playerAugment4": 0, "playerScore0": 0, "playerScore1": 0, "playerScore10": 0, "playerScore11": 0, "playerScore2": 0, "playerScore3": 0, "playerScore4": 0, "playerScore5": 0, "playerScore6": 0, "playerScore7": 0, "playerScore8": 0, "playerScore9": 0, "playerSubteamId": 0, "profileIcon": 7, "pushPings": 0, "puuid": "OEYoN1cDClAhcIpQidBjQK3S8GQalS9ortO3FcOz93fjt14LacUkXDHglYzz0RdzeHhv7yYt9ZcmiQ", "quadraKills": 0, "riotIdName": "", "riotIdTagline": "", "role": "SUPPORT", "sightWardsBoughtInGame": 0, "spell1Casts": 44, "spell2Casts": 27, "spell3Casts": 25, "spell4Casts": 11, "subteamPlacement": 0, "summoner1Casts": 8, "summoner1Id": 14, "summoner2Casts": 9, "summoner2Id": 4, "summonerId": "Y7GWXgxzgHS2mXhaWDrk107PDkAWL8oy89X7wiV0EDMTnqs", "summonerLevel": 45, "summonerName": "Air blower", "teamEarlySurrendered": false, "teamId": 100, "teamPosition": "UTILITY", "timeCCingOthers": 47, "timePlayed": 1860, "totalAllyJungleMinionsKilled": 0, "totalDamageDealt": 20695, "totalDamageDealtToChampions": 9829, "totalDamageShieldedOnTeammates": 2520, "totalDamageTaken": 23749, "totalEnemyJungleMinionsKilled": 0, "totalHeal": 1900, "totalHealsOnTeammates": 0, "totalMinionsKilled": 32, "totalTimeCCDealt": 263, "totalTimeSpentDead": 131, "totalUnitsHealed": 1, "tripleKills": 0, "trueDamageDealt": 4449, "trueDamageDealtToChampions": 1260, "trueDamageTaken": 1879, "turretKills": 0, "turretTakedowns": 0, "turretsLost": 10, "unrealKills": 0, "visionClearedPings": 0, "visionScore": 90, "visionWardsBoughtInGame": 12, "wardsKilled": 10, "wardsPlaced": 42, "win": false}, {"allInPings": 0, "assistMePings": 3, "assists": 3, "baitPings": 0, "baronKills": 0, "basicPings": 0, "bountyLevel": 8, "challenges": {"12AssistStreakCount": 0, "abilityUses": 453, "acesBefore15Minutes": 0, "alliedJungleMonsterKills": 6, "baronTakedowns": 1, "blastConeOppositeOpponentCount": 0, "bountyGold": 550, "buffsStolen": 0, "completeSupportQuestInTime": 0, "controlWardTimeCoverageInRiverOrEnemyHalf": 0.7968580698125894, "controlWardsPlaced": 1, "damagePerMinute": 992.1371868193045, "damageTakenOnTeamPercentage": 0.22005746582882701, "dancedWithRiftHerald": 0, "deathsByEnemyChamps": 4, "dodgeSkillShotsSmallWindow": 1, "doubleAces": 0, "dragonTakedowns": 1, "earliestBaron": 1602.9604843999998, "earliestDragonTakedown": 1457.9311245, "earlyLaningPhaseGoldExpAdvantage": 1, "effectiveHealAndShielding": 0, "elderDragonKillsWithOpposingSoul": 0, "elderDragonMultikills": 0, "enemyChampionImmobilizations": 39, "enemyJungleMonsterKills": 11, "epicMonsterKillsNearEnemyJungler": 0, "epicMonsterKillsWithin30SecondsOfSpawn": 0, "epicMonsterSteals": 0, "epicMonsterStolenWithoutSmite": 0, "fastestLegendary": 1746.9292074, "firstTurretKilled": 1, "firstTurretKilledTime": 890.8579205999999, "flawlessAces": 1, "fullTeamTakedown": 0, "gameLength": 1860.8363302999999, "getTakedownsInAllLanesEarlyJungleAsLaner": 0, "goldPerMinute": 579.195971564163, "hadOpenNexus": 0, "immobilizeAndKillWithAlly": 2, "initialBuffCount": 0, "initialCrabCount": 0, "jungleCsBefore10Minutes": 0, "junglerTakedownsNearDamagedEpicMonster": 0, "kTurretsDestroyedBeforePlatesFall": 0, "kda": 3.5, "killAfterHiddenWithAlly": 0, "killParticipation": 0.45161290322580644, "killedChampTookFullTeamDamageSurvived": 0, "killingSprees": 1, "killsNearEnemyTurret": 2, "killsOnOtherLanesEarlyJungleAsLaner": 1, "killsOnRecentlyHealedByAramPack": 0, "killsUnderOwnTurret": 0, "killsWithHelpFromEpicMonster": 0, "knockEnemyIntoTeamAndKill": 0, "landSkillShotsEarlyGame": 1, "laneMinionsFirst10Minutes": 76, "laningPhaseGoldExpAdvantage": 0, "legendaryCount": 1, "lostAnInhibitor": 0, "maxCsAdvantageOnLaneOpponent": 133.80000004172325, "maxKillDeficit": 13, "maxLevelLeadLaneOpponent": 4, "mejaisFullStackInTime": 0, "moreEnemyJungleThanOpponent": 0, "multiKillOneSpell": 0, "multiTurretRiftHeraldCount": 0, "multikills": 0, "multikillsAfterAggressiveFlash": 0, "mythicItemUsed": 3031, "outerTurretExecutesBefore10Minutes": 0, "outnumberedKills": 4, "outnumberedNexusKill": 0, "perfectDragonSoulsTaken": 0, "perfectGame": 0, "pickKillWithAlly": 8, "poroExplosions": 0, "quickCleanse": 0, "quickFirstTurret": 0, "quickSoloKills": 1, "riftHeraldTakedowns": 1, "saveAllyFromDeath": 0, "scuttleCrabKills": 2, "skillshotsDodged": 20, "skillshotsHit": 12, "snowballsHit": 0, "soloBaronKills": 0, "soloKills": 5, "soloTurretsLategame": 2, "stealthWardsPlaced": 5, "survivedSingleDigitHpCount": 0, "survivedThreeImmobilizesInFight": 2, "takedownOnFirstTurret": 0, "takedowns": 14, "takedownsAfterGainingLevelAdvantage": 0, "takedownsBeforeJungleMinionSpawn": 0, "takedownsFirstXMinutes": 4, "takedownsInAlcove": 0, "takedownsInEnemyFountain": 0, "teamBaronKills": 1, "teamDamagePercentage": 0.27909965769891854, "teamElderDragonKills": 0, "teamRiftHeraldKills": 1, "tookLargeDamageSurvived": 0, "turretPlatesTaken": 4, "turretTakedowns": 5, "turretsTakenWithRiftHerald": 0, "twentyMinionsIn3SecondsCount": 0, "twoWardsOneSweeperCount": 0, "unseenRecalls": 0, "visionScoreAdvantageLaneOpponent": 2.0502631664276123, "visionScorePerMinute": 1.0107248157219892, "wardTakedowns": 4, "wardTakedownsBefore20M": 1, "wardsGuarded": 0}, "champExperience": 20772, "champLevel": 18, "championId": 777, "championName": "Yone", "championTransform": 0, "commandPings": 6, "consumablesPurchased": 3, "damageDealtToBuildings": 11311, "damageDealtToObjectives": 37984, "damageDealtToTurrets": 11311, "damageSelfMitigated": 26170, "dangerPings": 0, "deaths": 4, "detectorWardsPlaced": 1, "doubleKills": 0, "dragonKills": 1, "eligibleForProgression": true, "enemyMissingPings": 18, "enemyVisionPings": 3, "firstBloodAssist": false, "firstBloodKill": false, "firstTowerAssist": false, "firstTowerKill": false, "gameEndedInEarlySurrender": false, "gameEndedInSurrender": true, "getBackPings": 0, "goldEarned": 17963, "goldSpent": 15250, "holdPings": 0, "individualPosition": "MIDDLE", "inhibitorKills": 0, "inhibitorTakedowns": 1, "inhibitorsLost": 0, "item0": 3026, "item1": 3006, "item2": 3031, "item3": 6673, "item4": 3133, "item5": 6672, "item6": 3363, "itemsPurchased": 21, "killingSprees": 2, "kills": 11, "lane": "BOTTOM", "largestCriticalStrike": 1425, "largestKillingSpree": 8, "largestMultiKill": 1, "longestTimeSpentLiving": 321, "magicDamageDealt": 36281, "magicDamageDealtToChampions": 5394, "magicDamageTaken": 5760, "missions": {"playerScore0": 0, "playerScore1": 0, "playerScore10": 0, "playerScore11": 0, "playerScore2": 0, "playerScore3": 0, "playerScore4": 0, "playerScore5": 0, "playerScore6": 0, "playerScore7": 0, "playerScore8": 0, "playerScore9": 0}, "needVisionPings": 0, "neutralMinionsKilled": 36, "nexusKills": 0, "nexusLost": 0, "nexusTakedowns": 0, "objectivesStolen": 0, "objectivesStolenAssists": 0, "onMyWayPings": 8, "participantId": 6, "pentaKills": 0, "perks": {"statPerks": {"defense": 5003, "flex": 5008, "offense": 5005}, "styles": [{"description": "primaryStyle", "selections": [{"perk": 8008, "var1": 63, "var2": 1, "var3": 0}, {"perk": 9111, "var1": 1062, "var2": 280, "var3": 0}, {"perk": 9104, "var1": 15, "var2": 0, "var3": 0}, {"perk": 8299, "var1": 785, "var2": 0, "var3": 0}], "style": 8000}, {"description": "subStyle", "selections": [{"perk": 8446, "var1": 3540, "var2": 0, "var3": 0}, {"perk": 8242, "var1": 84, "var2": 0, "var3": 0}], "style": 8400}]}, "physicalDamageDealt": 258820, "physicalDamageDealtToChampions": 21551, "physicalDamageTaken": 19609, "placement": 0, "playerAugment1": 0, "playerAugment2": 0, "playerAugment3": 0, "playerAugment4": 0, "playerScore0": 0, "playerScore1": 0, "playerScore10": 0, "playerScore11": 0, "playerScore2": 0, "playerScore3": 0, "playerScore4": 0, "playerScore5": 0, "playerScore6": 0, "playerScore7": 0, "playerScore8": 0, "playerScore9": 0, "playerSubteamId": 0, "profileIcon": 6332, "pushPings": 0, "puuid": "4DFcT0Oe5vG4RiempGzpAZrumxrkWMqbUQO8APQeYQkaqc8Aq17xtYIKjTmoCm0BGtrpawkAEgMEyA", "quadraKills": 0, "riotIdName": "", "riotIdTagline": "", "role": "DUO", "sightWardsBoughtInGame": 0, "spell1Casts": 308, "spell2Casts": 90, "spell3Casts": 46, "spell4Casts": 9, "subteamPlacement": 0, "summoner1Casts": 5, "summoner1Id": 12, "summoner2Casts": 4, "summoner2Id": 4, "summonerId": "zAsPxxzNqFgq52iK8T5yOpCMEZWidQsJiYEA2vF9daP-TDM", "summonerLevel": 648, "summonerName": "           lxyz", "teamEarlySurrendered": false, "teamId": 200, "teamPosition": "MIDDLE", "timeCCingOthers": 23, "timePlayed": 1860, "totalAllyJungleMinionsKilled": 4, "totalDamageDealt": 303444, "totalDamageDealtToChampions": 30770, "totalDamageShieldedOnTeammates": 0, "totalDamageTaken": 26166, "totalEnemyJungleMinionsKilled": 17, "totalHeal": 10639, "totalHealsOnTeammates": 0, "totalMinionsKilled": 264, "totalTimeCCDealt": 184, "totalTimeSpentDead": 87, "totalUnitsHealed": 1, "tripleKills": 0, "trueDamageDealt": 8342, "trueDamageDealtToChampions": 3824, "trueDamageTaken": 796, "turretKills": 5, "turretTakedowns": 5, "turretsLost": 3, "unrealKills": 0, "visionClearedPings": 0, "visionScore": 31, "visionWardsBoughtInGame": 2, "wardsKilled": 4, "wardsPlaced": 8, "win": true}, {"allInPings": 1, "assistMePings": 4, "assists": 17, "baitPings": 0, "baronKills": 1, "basicPings": 0, "bountyLevel": 0, "challenges": {"12AssistStreakCount": 1, "abilityUses": 410, "acesBefore15Minutes": 0, "alliedJungleMonsterKills": 92, "baronTakedowns": 1, "blastConeOppositeOpponentCount": 0, "bountyGold": 150, "buffsStolen": 2, "completeSupportQuestInTime": 0, "controlWardTimeCoverageInRiverOrEnemyHalf": 0.6264500518495707, "controlWardsPlaced": 1, "damagePerMinute": 656.6057844756924, "damageTakenOnTeamPercentage": 0.2782144989064022, "dancedWithRiftHerald": 0, "deathsByEnemyChamps": 4, "dodgeSkillShotsSmallWindow": 0, "doubleAces": 0, "dragonTakedowns": 2, "earliestBaron": 1602.9604843999998, "earliestDragonTakedown": 1125.1480817, "earlyLaningPhaseGoldExpAdvantage": 0, "effectiveHealAndShielding": 0, "elderDragonKillsWithOpposingSoul": 0, "elderDragonMultikills": 0, "enemyChampionImmobilizations": 31, "enemyJungleMonsterKills": 19, "epicMonsterKillsNearEnemyJungler": 0, "epicMonsterKillsWithin30SecondsOfSpawn": 2, "epicMonsterSteals": 0, "epicMonsterStolenWithoutSmite": 0, "firstTurretKilled": 1, "firstTurretKilledTime": 890.8579205999999, "flawlessAces": 1, "fullTeamTakedown": 0, "gameLength": 1860.8363302999999, "goldPerMinute": 432.7941837287548, "hadOpenNexus": 0, "immobilizeAndKillWithAlly": 13, "initialBuffCount": 3, "initialCrabCount": 0, "jungleCsBefore10Minutes": 55.50000008940697, "junglerKillsEarlyJungle": 0, "junglerTakedownsNearDamagedEpicMonster": 0, "kTurretsDestroyedBeforePlatesFall": 0, "kda": 5, "killAfterHiddenWithAlly": 1, "killParticipation": 0.6451612903225806, "killedChampTookFullTeamDamageSurvived": 0, "killingSprees": 0, "killsNearEnemyTurret": 2, "killsOnLanersEarlyJungleAsJungler": 0, "killsOnRecentlyHealedByAramPack": 0, "killsUnderOwnTurret": 0, "killsWithHelpFromEpicMonster": 1, "knockEnemyIntoTeamAndKill": 0, "landSkillShotsEarlyGame": 0, "laneMinionsFirst10Minutes": 4, "laningPhaseGoldExpAdvantage": 0, "legendaryCount": 0, "lostAnInhibitor": 0, "maxCsAdvantageOnLaneOpponent": 89.30000019073486, "maxKillDeficit": 13, "maxLevelLeadLaneOpponent": 4, "mejaisFullStackInTime": 0, "moreEnemyJungleThanOpponent": -21.000000089406967, "multiKillOneSpell": 0, "multiTurretRiftHeraldCount": 0, "multikills": 0, "multikillsAfterAggressiveFlash": 0, "mythicItemUsed": 6630, "outerTurretExecutesBefore10Minutes": 0, "outnumberedKills": 1, "outnumberedNexusKill": 0, "perfectDragonSoulsTaken": 0, "perfectGame": 0, "pickKillWithAlly": 18, "playedChampSelectPosition": 1, "poroExplosions": 0, "quickCleanse": 0, "quickFirstTurret": 0, "quickSoloKills": 0, "riftHeraldTakedowns": 0, "saveAllyFromDeath": 0, "scuttleCrabKills": 2, "shortestTimeToAceFromFirstTakedown": 14.9628024000001, "skillshotsDodged": 29, "skillshotsHit": 0, "snowballsHit": 0, "soloBaronKills": 0, "soloKills": 0, "stealthWardsPlaced": 1, "survivedSingleDigitHpCount": 0, "survivedThreeImmobilizesInFight": 6, "takedownOnFirstTurret": 0, "takedowns": 20, "takedownsAfterGainingLevelAdvantage": 0, "takedownsBeforeJungleMinionSpawn": 0, "takedownsFirstXMinutes": 6, "takedownsInAlcove": 0, "takedownsInEnemyFountain": 0, "teamBaronKills": 1, "teamDamagePercentage": 0.18471079617306194, "teamElderDragonKills": 0, "teamRiftHeraldKills": 1, "tookLargeDamageSurvived": 0, "turretPlatesTaken": 0, "turretTakedowns": 3, "turretsTakenWithRiftHerald": 0, "twentyMinionsIn3SecondsCount": 0, "twoWardsOneSweeperCount": 0, "unseenRecalls": 0, "visionScoreAdvantageLaneOpponent": -0.546480655670166, "visionScorePerMinute": 0.6117852176931072, "wardTakedowns": 3, "wardTakedownsBefore20M": 0, "wardsGuarded": 2}, "champExperience": 17356, "champLevel": 17, "championId": 59, "championName": "JarvanIV", "championTransform": 0, "commandPings": 24, "consumablesPurchased": 3, "damageDealtToBuildings": 1866, "damageDealtToObjectives": 19997, "damageDealtToTurrets": 1866, "damageSelfMitigated": 61765, "dangerPings": 0, "deaths": 4, "detectorWardsPlaced": 1, "doubleKills": 0, "dragonKills": 2, "eligibleForProgression": true, "enemyMissingPings": 23, "enemyVisionPings": 7, "firstBloodAssist": false, "firstBloodKill": false, "firstTowerAssist": false, "firstTowerKill": false, "gameEndedInEarlySurrender": false, "gameEndedInSurrender": true, "getBackPings": 3, "goldEarned": 13422, "goldSpent": 12050, "holdPings": 0, "individualPosition": "JUNGLE", "inhibitorKills": 1, "inhibitorTakedowns": 1, "inhibitorsLost": 0, "item0": 3161, "item1": 3047, "item2": 6630, "item3": 3110, "item4": 3133, "item5": 1029, "item6": 3364, "itemsPurchased": 21, "killingSprees": 1, "kills": 3, "lane": "JUNGLE", "largestCriticalStrike": 0, "largestKillingSpree": 2, "largestMultiKill": 1, "longestTimeSpentLiving": 507, "magicDamageDealt": 21738, "magicDamageDealtToChampions": 1445, "magicDamageTaken": 6953, "missions": {"playerScore0": 0, "playerScore1": 0, "playerScore10": 0, "playerScore11": 0, "playerScore2": 0, "playerScore3": 0, "playerScore4": 0, "playerScore5": 0, "playerScore6": 0, "playerScore7": 0, "playerScore8": 0, "playerScore9": 0}, "needVisionPings": 0, "neutralMinionsKilled": 182, "nexusKills": 0, "nexusLost": 0, "nexusTakedowns": 0, "objectivesStolen": 0, "objectivesStolenAssists": 0, "onMyWayPings": 18, "participantId": 7, "pentaKills": 0, "perks": {"statPerks": {"defense": 5002, "flex": 5008, "offense": 5005}, "styles": [{"description": "primaryStyle", "selections": [{"perk": 8010, "var1": 538, "var2": 0, "var3": 0}, {"perk": 9111, "var1": 2381, "var2": 400, "var3": 0}, {"perk": 9104, "var1": 14, "var2": 10, "var3": 0}, {"perk": 8014, "var1": 249, "var2": 0, "var3": 0}], "style": 8000}, {"description": "subStyle", "selections": [{"perk": 8304, "var1": 10, "var2": 3, "var3": 0}, {"perk": 8347, "var1": 0, "var2": 0, "var3": 0}], "style": 8300}]}, "physicalDamageDealt": 208912, "physicalDamageDealtToChampions": 17588, "physicalDamageTaken": 24759, "placement": 0, "playerAugment1": 0, "playerAugment2": 0, "playerAugment3": 0, "playerAugment4": 0, "playerScore0": 0, "playerScore1": 0, "playerScore10": 0, "playerScore11": 0, "playerScore2": 0, "playerScore3": 0, "playerScore4": 0, "playerScore5": 0, "playerScore6": 0, "playerScore7": 0, "playerScore8": 0, "playerScore9": 0, "playerSubteamId": 0, "profileIcon": 6362, "pushPings": 1, "puuid": "eTqwVzqEpeTX4VWN_vQ5VkU1JiY0Ku5Ltiikv4EqFprCbbmR0UM0RY87XFC901xo97Ona1qmQZC27g", "quadraKills": 0, "riotIdName": "", "riotIdTagline": "", "role": "NONE", "sightWardsBoughtInGame": 0, "spell1Casts": 163, "spell2Casts": 104, "spell3Casts": 134, "spell4Casts": 9, "subteamPlacement": 0, "summoner1Casts": 21, "summoner1Id": 11, "summoner2Casts": 5, "summoner2Id": 4, "summonerId": "r3ZD7Auiygj6iGQj5crHoCQQ3GxQ1qScLKkmLcp8o7yOSyU", "summonerLevel": 387, "summonerName": "\ub3cc \ub3cc", "teamEarlySurrendered": false, "teamId": 200, "teamPosition": "JUNGLE", "timeCCingOthers": 46, "timePlayed": 1860, "totalAllyJungleMinionsKilled": 130, "totalDamageDealt": 285893, "totalDamageDealtToChampions": 20363, "totalDamageShieldedOnTeammates": 0, "totalDamageTaken": 33081, "totalEnemyJungleMinionsKilled": 25, "totalHeal": 16200, "totalHealsOnTeammates": 0, "totalMinionsKilled": 45, "totalTimeCCDealt": 967, "totalTimeSpentDead": 107, "totalUnitsHealed": 1, "tripleKills": 0, "trueDamageDealt": 55241, "trueDamageDealtToChampions": 1329, "trueDamageTaken": 1369, "turretKills": 0, "turretTakedowns": 3, "turretsLost": 3, "unrealKills": 0, "visionClearedPings": 0, "visionScore": 18, "visionWardsBoughtInGame": 2, "wardsKilled": 3, "wardsPlaced": 2, "win": true}, {"allInPings": 0, "assistMePings": 0, "assists": 14, "baitPings": 0, "baronKills": 0, "basicPings": 0, "bountyLevel": 0, "challenges": {"12AssistStreakCount": 1, "abilityUses": 410, "acesBefore15Minutes": 0, "alliedJungleMonsterKills": 0, "baronTakedowns": 1, "blastConeOppositeOpponentCount": 0, "bountyGold": 0, "buffsStolen": 0, "completeSupportQuestInTime": 0, "controlWardTimeCoverageInRiverOrEnemyHalf": 0.7574336977679117, "controlWardsPlaced": 9, "damagePerMinute": 423.79640237374406, "damageTakenOnTeamPercentage": 0.1591629150399744, "dancedWithRiftHerald": 0, "deathsByEnemyChamps": 8, "dodgeSkillShotsSmallWindow": 0, "doubleAces": 0, "dragonTakedowns": 1, "earliestBaron": 1602.9604843999998, "earliestDragonTakedown": 1766.6072763999998, "earlyLaningPhaseGoldExpAdvantage": 0, "effectiveHealAndShielding": 1775.439697265625, "elderDragonKillsWithOpposingSoul": 0, "elderDragonMultikills": 0, "enemyChampionImmobilizations": 22, "enemyJungleMonsterKills": 0, "epicMonsterKillsNearEnemyJungler": 0, "epicMonsterKillsWithin30SecondsOfSpawn": 0, "epicMonsterSteals": 0, "epicMonsterStolenWithoutSmite": 0, "firstTurretKilled": 1, "firstTurretKilledTime": 890.8579205999999, "flawlessAces": 1, "fullTeamTakedown": 0, "gameLength": 1860.8363302999999, "getTakedownsInAllLanesEarlyJungleAsLaner": 0, "goldPerMinute": 311.44218341549004, "hadOpenNexus": 0, "immobilizeAndKillWithAlly": 3, "initialBuffCount": 0, "initialCrabCount": 0, "jungleCsBefore10Minutes": 0, "junglerTakedownsNearDamagedEpicMonster": 0, "kTurretsDestroyedBeforePlatesFall": 0, "kda": 1.875, "killAfterHiddenWithAlly": 0, "killParticipation": 0.4838709677419355, "killedChampTookFullTeamDamageSurvived": 0, "killingSprees": 0, "killsNearEnemyTurret": 1, "killsOnOtherLanesEarlyJungleAsLaner": 0, "killsOnRecentlyHealedByAramPack": 0, "killsUnderOwnTurret": 0, "killsWithHelpFromEpicMonster": 0, "knockEnemyIntoTeamAndKill": 3, "landSkillShotsEarlyGame": 11, "laneMinionsFirst10Minutes": 54, "laningPhaseGoldExpAdvantage": 0, "legendaryCount": 0, "lostAnInhibitor": 0, "maxCsAdvantageOnLaneOpponent": 4, "maxKillDeficit": 13, "maxLevelLeadLaneOpponent": 1, "mejaisFullStackInTime": 0, "moreEnemyJungleThanOpponent": 0, "multiKillOneSpell": 0, "multiTurretRiftHeraldCount": 0, "multikills": 0, "multikillsAfterAggressiveFlash": 0, "mythicItemUsed": 4644, "outerTurretExecutesBefore10Minutes": 0, "outnumberedKills": 1, "outnumberedNexusKill": 0, "perfectDragonSoulsTaken": 0, "perfectGame": 0, "pickKillWithAlly": 13, "poroExplosions": 0, "quickCleanse": 0, "quickFirstTurret": 0, "quickSoloKills": 0, "riftHeraldTakedowns": 1, "saveAllyFromDeath": 0, "scuttleCrabKills": 0, "shortestTimeToAceFromFirstTakedown": 14.9628024000001, "skillshotsDodged": 30, "skillshotsHit": 42, "snowballsHit": 0, "soloBaronKills": 0, "soloKills": 0, "stealthWardsPlaced": 5, "survivedSingleDigitHpCount": 0, "survivedThreeImmobilizesInFight": 0, "takedownOnFirstTurret": 0, "takedowns": 15, "takedownsAfterGainingLevelAdvantage": 0, "takedownsBeforeJungleMinionSpawn": 0, "takedownsFirstXMinutes": 6, "takedownsInAlcove": 0, "takedownsInEnemyFountain": 0, "teamBaronKills": 1, "teamDamagePercentage": 0.11921882619453454, "teamElderDragonKills": 0, "teamRiftHeraldKills": 1, "tookLargeDamageSurvived": 0, "turretPlatesTaken": 0, "turretTakedowns": 3, "turretsTakenWithRiftHerald": 0, "twentyMinionsIn3SecondsCount": 0, "twoWardsOneSweeperCount": 0, "unseenRecalls": 0, "visionScoreAdvantageLaneOpponent": 0.1637212038040161, "visionScorePerMinute": 1.11545859717481, "wardTakedowns": 2, "wardTakedownsBefore20M": 0, "wardsGuarded": 0}, "champExperience": 13482, "champLevel": 15, "championId": 61, "championName": "Orianna", "championTransform": 0, "commandPings": 18, "consumablesPurchased": 11, "damageDealtToBuildings": 2578, "damageDealtToObjectives": 7121, "damageDealtToTurrets": 2578, "damageSelfMitigated": 12352, "dangerPings": 0, "deaths": 8, "detectorWardsPlaced": 9, "doubleKills": 0, "dragonKills": 0, "eligibleForProgression": true, "enemyMissingPings": 3, "enemyVisionPings": 1, "firstBloodAssist": false, "firstBloodKill": false, "firstTowerAssist": true, "firstTowerKill": false, "gameEndedInEarlySurrender": false, "gameEndedInSurrender": true, "getBackPings": 0, "goldEarned": 9659, "goldSpent": 9675, "holdPings": 0, "individualPosition": "TOP", "inhibitorKills": 1, "inhibitorTakedowns": 2, "inhibitorsLost": 0, "item0": 0, "item1": 0, "item2": 2420, "item3": 3040, "item4": 4644, "item5": 3020, "item6": 3363, "itemsPurchased": 25, "killingSprees": 0, "kills": 1, "lane": "TOP", "largestCriticalStrike": 0, "largestKillingSpree": 0, "largestMultiKill": 1, "longestTimeSpentLiving": 369, "magicDamageDealt": 93025, "magicDamageDealtToChampions": 12095, "magicDamageTaken": 2811, "missions": {"playerScore0": 0, "playerScore1": 0, "playerScore10": 0, "playerScore11": 0, "playerScore2": 0, "playerScore3": 0, "playerScore4": 0, "playerScore5": 0, "playerScore6": 0, "playerScore7": 0, "playerScore8": 0, "playerScore9": 0}, "needVisionPings": 0, "neutralMinionsKilled": 0, "nexusKills": 0, "nexusLost": 0, "nexusTakedowns": 0, "objectivesStolen": 0, "objectivesStolenAssists": 0, "onMyWayPings": 2, "participantId": 8, "pentaKills": 0, "perks": {"statPerks": {"defense": 5002, "flex": 5008, "offense": 5005}, "styles": [{"description": "primaryStyle", "selections": [{"perk": 8230, "var1": 13, "var2": 0, "var3": 0}, {"perk": 8226, "var1": 250, "var2": 1542, "var3": 0}, {"perk": 8210, "var1": 5, "var2": 0, "var3": 0}, {"perk": 8237, "var1": 535, "var2": 0, "var3": 0}], "style": 8200}, {"description": "subStyle", "selections": [{"perk": 8345, "var1": 3, "var2": 0, "var3": 0}, {"perk": 8347, "var1": 0, "var2": 0, "var3": 0}], "style": 8300}]}, "physicalDamageDealt": 12605, "physicalDamageDealtToChampions": 1005, "physicalDamageTaken": 15574, "placement": 0, "playerAugment1": 0, "playerAugment2": 0, "playerAugment3": 0, "playerAugment4": 0, "playerScore0": 0, "playerScore1": 0, "playerScore10": 0, "playerScore11": 0, "playerScore2": 0, "playerScore3": 0, "playerScore4": 0, "playerScore5": 0, "playerScore6": 0, "playerScore7": 0, "playerScore8": 0, "playerScore9": 0, "playerSubteamId": 0, "profileIcon": 29, "pushPings": 0, "puuid": "417JybcWTqo0tlsto42SFnhEFWvVlywYXwql41jjwzL1EqwkjnfU_Aj_97-WJEDE8H0aug753Zn58w", "quadraKills": 0, "riotIdName": "", "riotIdTagline": "", "role": "SOLO", "sightWardsBoughtInGame": 0, "spell1Casts": 177, "spell2Casts": 152, "spell3Casts": 71, "spell4Casts": 10, "subteamPlacement": 0, "summoner1Casts": 5, "summoner1Id": 3, "summoner2Casts": 4, "summoner2Id": 4, "summonerId": "TvMHBqIz7PA7rG-p01vKSMTkM2YN6T6I8z2_I44Ztw0Emz0", "summonerLevel": 306, "summonerName": "T1 Faker\ucc98\ub7fc", "teamEarlySurrendered": false, "teamId": 200, "teamPosition": "TOP", "timeCCingOthers": 27, "timePlayed": 1860, "totalAllyJungleMinionsKilled": 0, "totalDamageDealt": 105772, "totalDamageDealtToChampions": 13143, "totalDamageShieldedOnTeammates": 1775, "totalDamageTaken": 18925, "totalEnemyJungleMinionsKilled": 0, "totalHeal": 2305, "totalHealsOnTeammates": 0, "totalMinionsKilled": 148, "totalTimeCCDealt": 341, "totalTimeSpentDead": 173, "totalUnitsHealed": 1, "tripleKills": 0, "trueDamageDealt": 142, "trueDamageDealtToChampions": 42, "trueDamageTaken": 539, "turretKills": 2, "turretTakedowns": 3, "turretsLost": 3, "unrealKills": 0, "visionClearedPings": 0, "visionScore": 34, "visionWardsBoughtInGame": 9, "wardsKilled": 2, "wardsPlaced": 17, "win": true}, {"allInPings": 9, "assistMePings": 12, "assists": 1, "baitPings": 0, "baronKills": 0, "basicPings": 0, "bountyLevel": 5, "challenges": {"12AssistStreakCount": 0, "abilityUses": 387, "acesBefore15Minutes": 0, "alliedJungleMonsterKills": 0, "baronTakedowns": 1, "blastConeOppositeOpponentCount": 0, "bountyGold": 750, "buffsStolen": 0, "completeSupportQuestInTime": 0, "controlWardsPlaced": 0, "damagePerMinute": 1094.4034518052854, "damageTakenOnTeamPercentage": 0.17416665136351417, "dancedWithRiftHerald": 0, "deathsByEnemyChamps": 5, "dodgeSkillShotsSmallWindow": 0, "doubleAces": 0, "dragonTakedowns": 3, "earliestBaron": 1602.9604843999998, "earliestDragonTakedown": 1125.1480817, "earlyLaningPhaseGoldExpAdvantage": 0, "effectiveHealAndShielding": 0, "elderDragonKillsWithOpposingSoul": 0, "elderDragonMultikills": 0, "enemyChampionImmobilizations": 15, "enemyJungleMonsterKills": 0, "epicMonsterKillsNearEnemyJungler": 0, "epicMonsterKillsWithin30SecondsOfSpawn": 0, "epicMonsterSteals": 0, "epicMonsterStolenWithoutSmite": 0, "fastestLegendary": 1565.0910385, "firstTurretKilled": 1, "firstTurretKilledTime": 890.8579205999999, "flawlessAces": 1, "fullTeamTakedown": 0, "gameLength": 1860.8363302999999, "getTakedownsInAllLanesEarlyJungleAsLaner": 0, "goldPerMinute": 584.3932314427041, "hadOpenNexus": 0, "highestChampionDamage": 1, "immobilizeAndKillWithAlly": 5, "initialBuffCount": 0, "initialCrabCount": 0, "jungleCsBefore10Minutes": 0, "junglerTakedownsNearDamagedEpicMonster": 0, "kTurretsDestroyedBeforePlatesFall": 0, "kda": 3.2, "killAfterHiddenWithAlly": 1, "killParticipation": 0.5161290322580645, "killedChampTookFullTeamDamageSurvived": 0, "killingSprees": 2, "killsNearEnemyTurret": 5, "killsOnOtherLanesEarlyJungleAsLaner": 0, "killsOnRecentlyHealedByAramPack": 0, "killsUnderOwnTurret": 3, "killsWithHelpFromEpicMonster": 0, "knockEnemyIntoTeamAndKill": 5, "landSkillShotsEarlyGame": 1, "laneMinionsFirst10Minutes": 89, "laningPhaseGoldExpAdvantage": 0, "legendaryCount": 1, "lostAnInhibitor": 0, "maxCsAdvantageOnLaneOpponent": 39, "maxKillDeficit": 13, "maxLevelLeadLaneOpponent": 2, "mejaisFullStackInTime": 0, "moreEnemyJungleThanOpponent": 0, "multiKillOneSpell": 0, "multiTurretRiftHeraldCount": 0, "multikills": 5, "multikillsAfterAggressiveFlash": 1, "mythicItemUsed": 3142, "outerTurretExecutesBefore10Minutes": 0, "outnumberedKills": 6, "outnumberedNexusKill": 0, "perfectDragonSoulsTaken": 0, "perfectGame": 0, "pickKillWithAlly": 15, "playedChampSelectPosition": 1, "poroExplosions": 0, "quickCleanse": 0, "quickFirstTurret": 0, "quickSoloKills": 1, "riftHeraldTakedowns": 0, "saveAllyFromDeath": 0, "scuttleCrabKills": 1, "shortestTimeToAceFromFirstTakedown": 14.9628024000001, "skillshotsDodged": 17, "skillshotsHit": 32, "snowballsHit": 0, "soloBaronKills": 0, "soloKills": 1, "stealthWardsPlaced": 11, "survivedSingleDigitHpCount": 0, "survivedThreeImmobilizesInFight": 2, "takedownOnFirstTurret": 1, "takedowns": 16, "takedownsAfterGainingLevelAdvantage": 0, "takedownsBeforeJungleMinionSpawn": 0, "takedownsFirstXMinutes": 1, "takedownsInAlcove": 1, "takedownsInEnemyFountain": 0, "teamBaronKills": 1, "teamDamagePercentage": 0.30786834002523933, "teamElderDragonKills": 0, "teamRiftHeraldKills": 1, "tookLargeDamageSurvived": 0, "turretPlatesTaken": 2, "turretTakedowns": 1, "turretsTakenWithRiftHerald": 0, "twentyMinionsIn3SecondsCount": 0, "twoWardsOneSweeperCount": 0, "unseenRecalls": 0, "visionScoreAdvantageLaneOpponent": 0.08456146717071533, "visionScorePerMinute": 0.8100175807907215, "wardTakedowns": 3, "wardTakedownsBefore20M": 2, "wardsGuarded": 0}, "champExperience": 15594, "champLevel": 16, "championId": 119, "championName": "Draven", "championTransform": 0, "commandPings": 10, "consumablesPurchased": 1, "damageDealtToBuildings": 709, "damageDealtToObjectives": 26923, "damageDealtToTurrets": 709, "damageSelfMitigated": 13259, "dangerPings": 0, "deaths": 5, "detectorWardsPlaced": 0, "doubleKills": 2, "dragonKills": 0, "eligibleForProgression": true, "enemyMissingPings": 0, "enemyVisionPings": 3, "firstBloodAssist": false, "firstBloodKill": false, "firstTowerAssist": false, "firstTowerKill": true, "gameEndedInEarlySurrender": false, "gameEndedInSurrender": true, "getBackPings": 1, "goldEarned": 18124, "goldSpent": 14650, "holdPings": 0, "individualPosition": "BOTTOM", "inhibitorKills": 0, "inhibitorTakedowns": 0, "inhibitorsLost": 0, "item0": 3142, "item1": 3033, "item2": 3508, "item3": 3006, "item4": 6676, "item5": 1053, "item6": 3340, "itemsPurchased": 24, "killingSprees": 2, "kills": 15, "lane": "BOTTOM", "largestCriticalStrike": 1118, "largestKillingSpree": 9, "largestMultiKill": 5, "longestTimeSpentLiving": 731, "magicDamageDealt": 0, "magicDamageDealtToChampions": 0, "magicDamageTaken": 4171, "missions": {"playerScore0": 0, "playerScore1": 0, "playerScore10": 0, "playerScore11": 0, "playerScore2": 0, "playerScore3": 0, "playerScore4": 0, "playerScore5": 0, "playerScore6": 0, "playerScore7": 0, "playerScore8": 0, "playerScore9": 0}, "needVisionPings": 2, "neutralMinionsKilled": 4, "nexusKills": 0, "nexusLost": 0, "nexusTakedowns": 0, "objectivesStolen": 0, "objectivesStolenAssists": 0, "onMyWayPings": 26, "participantId": 9, "pentaKills": 1, "perks": {"statPerks": {"defense": 5002, "flex": 5008, "offense": 5005}, "styles": [{"description": "primaryStyle", "selections": [{"perk": 8008, "var1": 57, "var2": 8, "var3": 0}, {"perk": 9111, "var1": 987, "var2": 320, "var3": 0}, {"perk": 9103, "var1": 22, "var2": 30, "var3": 0}, {"perk": 8299, "var1": 485, "var2": 0, "var3": 0}], "style": 8000}, {"description": "subStyle", "selections": [{"perk": 8233, "var1": 22, "var2": 20, "var3": 0}, {"perk": 8236, "var1": 28, "var2": 0, "var3": 0}], "style": 8200}]}, "physicalDamageDealt": 217235, "physicalDamageDealtToChampions": 32862, "physicalDamageTaken": 16134, "placement": 0, "playerAugment1": 0, "playerAugment2": 0, "playerAugment3": 0, "playerAugment4": 0, "playerScore0": 0, "playerScore1": 0, "playerScore10": 0, "playerScore11": 0, "playerScore2": 0, "playerScore3": 0, "playerScore4": 0, "playerScore5": 0, "playerScore6": 0, "playerScore7": 0, "playerScore8": 0, "playerScore9": 0, "playerSubteamId": 0, "profileIcon": 5722, "pushPings": 0, "puuid": "jDmpMChlWbsg8jjtAPRggqCD_6wM5QuVYEm1paDLCxzoUctYJWruEiDECPyg_siAmakJ8Lerqt6yJw", "quadraKills": 1, "riotIdName": "", "riotIdTagline": "", "role": "DUO", "sightWardsBoughtInGame": 0, "spell1Casts": 105, "spell2Casts": 257, "spell3Casts": 14, "spell4Casts": 11, "subteamPlacement": 0, "summoner1Casts": 4, "summoner1Id": 4, "summoner2Casts": 5, "summoner2Id": 3, "summonerId": "TxediB9TY6zXV1z9y5m1k65__X-CdqB7v27mV0I7PQclr24", "summonerLevel": 639, "summonerName": "\uc720\ub2c8\ucf58 \ucef4\ud37c\ub2c8", "teamEarlySurrendered": false, "teamId": 200, "teamPosition": "BOTTOM", "timeCCingOthers": 15, "timePlayed": 1860, "totalAllyJungleMinionsKilled": 0, "totalDamageDealt": 225731, "totalDamageDealtToChampions": 33941, "totalDamageShieldedOnTeammates": 0, "totalDamageTaken": 20709, "totalEnemyJungleMinionsKilled": 0, "totalHeal": 6492, "totalHealsOnTeammates": 0, "totalMinionsKilled": 237, "totalTimeCCDealt": 111, "totalTimeSpentDead": 128, "totalUnitsHealed": 1, "tripleKills": 1, "trueDamageDealt": 8495, "trueDamageDealtToChampions": 1078, "trueDamageTaken": 404, "turretKills": 1, "turretTakedowns": 1, "turretsLost": 3, "unrealKills": 0, "visionClearedPings": 0, "visionScore": 25, "visionWardsBoughtInGame": 0, "wardsKilled": 3, "wardsPlaced": 11, "win": true}, {"allInPings": 2, "assistMePings": 0, "assists": 11, "baitPings": 0, "baronKills": 0, "basicPings": 0, "bountyLevel": 0, "challenges": {"12AssistStreakCount": 0, "abilityUses": 130, "acesBefore15Minutes": 0, "alliedJungleMonsterKills": 0, "baronTakedowns": 1, "blastConeOppositeOpponentCount": 0, "bountyGold": 300, "buffsStolen": 0, "completeSupportQuestInTime": 1, "controlWardTimeCoverageInRiverOrEnemyHalf": 0.860212991994807, "controlWardsPlaced": 3, "damagePerMinute": 387.8346866130078, "damageTakenOnTeamPercentage": 0.16839846886128218, "dancedWithRiftHerald": 0, "deathsByEnemyChamps": 10, "dodgeSkillShotsSmallWindow": 4, "doubleAces": 0, "dragonTakedowns": 0, "earliestBaron": 1602.9604843999998, "earlyLaningPhaseGoldExpAdvantage": 0, "effectiveHealAndShielding": 4186.68896484375, "elderDragonKillsWithOpposingSoul": 0, "elderDragonMultikills": 0, "enemyChampionImmobilizations": 27, "enemyJungleMonsterKills": 0, "epicMonsterKillsNearEnemyJungler": 1, "epicMonsterKillsWithin30SecondsOfSpawn": 0, "epicMonsterSteals": 0, "epicMonsterStolenWithoutSmite": 0, "fasterSupportQuestCompletion": 1, "firstTurretKilled": 1, "firstTurretKilledTime": 890.8579205999999, "flawlessAces": 1, "fullTeamTakedown": 0, "gameLength": 1860.8363302999999, "getTakedownsInAllLanesEarlyJungleAsLaner": 0, "goldPerMinute": 311.1812435368218, "hadOpenNexus": 0, "highestWardKills": 1, "immobilizeAndKillWithAlly": 3, "initialBuffCount": 0, "initialCrabCount": 0, "jungleCsBefore10Minutes": 0, "junglerTakedownsNearDamagedEpicMonster": 0, "kTurretsDestroyedBeforePlatesFall": 0, "kda": 1.2, "killAfterHiddenWithAlly": 0, "killParticipation": 0.3870967741935484, "killedChampTookFullTeamDamageSurvived": 0, "killingSprees": 0, "killsNearEnemyTurret": 1, "killsOnOtherLanesEarlyJungleAsLaner": 0, "killsOnRecentlyHealedByAramPack": 0, "killsUnderOwnTurret": 0, "killsWithHelpFromEpicMonster": 0, "knockEnemyIntoTeamAndKill": 0, "landSkillShotsEarlyGame": 6, "laneMinionsFirst10Minutes": 3, "laningPhaseGoldExpAdvantage": 0, "legendaryCount": 0, "lostAnInhibitor": 0, "maxCsAdvantageOnLaneOpponent": 8, "maxKillDeficit": 13, "maxLevelLeadLaneOpponent": 1, "mejaisFullStackInTime": 0, "moreEnemyJungleThanOpponent": 0, "multiKillOneSpell": 0, "multiTurretRiftHeraldCount": 0, "multikills": 0, "multikillsAfterAggressiveFlash": 0, "mythicItemUsed": 6692, "outerTurretExecutesBefore10Minutes": 0, "outnumberedKills": 0, "outnumberedNexusKill": 0, "perfectDragonSoulsTaken": 0, "perfectGame": 0, "pickKillWithAlly": 11, "playedChampSelectPosition": 1, "poroExplosions": 0, "quickCleanse": 0, "quickFirstTurret": 0, "quickSoloKills": 0, "riftHeraldTakedowns": 1, "saveAllyFromDeath": 0, "scuttleCrabKills": 0, "skillshotsDodged": 41, "skillshotsHit": 36, "snowballsHit": 0, "soloBaronKills": 0, "soloKills": 0, "stealthWardsPlaced": 26, "survivedSingleDigitHpCount": 0, "survivedThreeImmobilizesInFight": 0, "takedownOnFirstTurret": 0, "takedowns": 12, "takedownsAfterGainingLevelAdvantage": 0, "takedownsBeforeJungleMinionSpawn": 0, "takedownsFirstXMinutes": 4, "takedownsInAlcove": 0, "takedownsInEnemyFountain": 0, "teamBaronKills": 1, "teamDamagePercentage": 0.10910237990824563, "teamElderDragonKills": 0, "teamRiftHeraldKills": 1, "tookLargeDamageSurvived": 0, "turretPlatesTaken": 2, "turretTakedowns": 1, "turretsTakenWithRiftHerald": 0, "twentyMinionsIn3SecondsCount": 0, "twoWardsOneSweeperCount": 3, "unseenRecalls": 0, "visionScoreAdvantageLaneOpponent": -0.1012793779373169, "visionScorePerMinute": 2.610988923508229, "wardTakedowns": 17, "wardTakedownsBefore20M": 7, "wardsGuarded": 1}, "champExperience": 10647, "champLevel": 13, "championId": 235, "championName": "Senna", "championTransform": 0, "commandPings": 4, "consumablesPurchased": 5, "damageDealtToBuildings": 2828, "damageDealtToObjectives": 4725, "damageDealtToTurrets": 2828, "damageSelfMitigated": 10373, "dangerPings": 0, "deaths": 10, "detectorWardsPlaced": 3, "doubleKills": 0, "dragonKills": 0, "eligibleForProgression": true, "enemyMissingPings": 2, "enemyVisionPings": 10, "firstBloodAssist": false, "firstBloodKill": false, "firstTowerAssist": true, "firstTowerKill": false, "gameEndedInEarlySurrender": false, "gameEndedInSurrender": true, "getBackPings": 0, "goldEarned": 9650, "goldSpent": 8325, "holdPings": 0, "individualPosition": "UTILITY", "inhibitorKills": 0, "inhibitorTakedowns": 0, "inhibitorsLost": 0, "item0": 3864, "item1": 2015, "item2": 1018, "item3": 6692, "item4": 3179, "item5": 3009, "item6": 3364, "itemsPurchased": 23, "killingSprees": 0, "kills": 1, "lane": "BOTTOM", "largestCriticalStrike": 494, "largestKillingSpree": 0, "largestMultiKill": 1, "longestTimeSpentLiving": 216, "magicDamageDealt": 270, "magicDamageDealtToChampions": 80, "magicDamageTaken": 4862, "missions": {"playerScore0": 0, "playerScore1": 0, "playerScore10": 0, "playerScore11": 0, "playerScore2": 0, "playerScore3": 0, "playerScore4": 0, "playerScore5": 0, "playerScore6": 0, "playerScore7": 0, "playerScore8": 0, "playerScore9": 0}, "needVisionPings": 0, "neutralMinionsKilled": 4, "nexusKills": 0, "nexusLost": 0, "nexusTakedowns": 0, "objectivesStolen": 0, "objectivesStolenAssists": 0, "onMyWayPings": 0, "participantId": 10, "pentaKills": 0, "perks": {"statPerks": {"defense": 5002, "flex": 5008, "offense": 5005}, "styles": [{"description": "primaryStyle", "selections": [{"perk": 8021, "var1": 1031, "var2": 899, "var3": 0}, {"perk": 8009, "var1": 1674, "var2": 0, "var3": 0}, {"perk": 9104, "var1": 26, "var2": 40, "var3": 0}, {"perk": 8017, "var1": 1252, "var2": 0, "var3": 0}], "style": 8000}, {"description": "subStyle", "selections": [{"perk": 8410, "var1": 50, "var2": 0, "var3": 0}, {"perk": 8345, "var1": 3, "var2": 0, "var3": 0}], "style": 8300}]}, "physicalDamageDealt": 32917, "physicalDamageDealtToChampions": 11857, "physicalDamageTaken": 14753, "placement": 0, "playerAugment1": 0, "playerAugment2": 0, "playerAugment3": 0, "playerAugment4": 0, "playerScore0": 0, "playerScore1": 0, "playerScore10": 0, "playerScore11": 0, "playerScore2": 0, "playerScore3": 0, "playerScore4": 0, "playerScore5": 0, "playerScore6": 0, "playerScore7": 0, "playerScore8": 0, "playerScore9": 0, "playerSubteamId": 0, "profileIcon": 4568, "pushPings": 0, "puuid": "IG86ORX03RQCSUqgrHKs4MQfpRfGSxYIy6VO_ImiQ2c0BOZCdKsxaWZfbp9z2_KgIuJtg_-obrmszw", "quadraKills": 0, "riotIdName": "", "riotIdTagline": "", "role": "SUPPORT", "sightWardsBoughtInGame": 0, "spell1Casts": 64, "spell2Casts": 36, "spell3Casts": 24, "spell4Casts": 6, "subteamPlacement": 0, "summoner1Casts": 5, "summoner1Id": 7, "summoner2Casts": 5, "summoner2Id": 4, "summonerId": "nVVFFuV_7kucuOyDBBML1Cfw0Ou-w8TrhVZqACp4-YPwk7U", "summonerLevel": 63, "summonerName": "\ub9cc\uae30\uc804\uc5ed\ud55c\ub098\uc774", "teamEarlySurrendered": false, "teamId": 200, "teamPosition": "UTILITY", "timeCCingOthers": 38, "timePlayed": 1860, "totalAllyJungleMinionsKilled": 0, "totalDamageDealt": 33312, "totalDamageDealtToChampions": 12028, "totalDamageShieldedOnTeammates": 1016, "totalDamageTaken": 20023, "totalEnemyJungleMinionsKilled": 0, "totalHeal": 8508, "totalHealsOnTeammates": 3170, "totalMinionsKilled": 36, "totalTimeCCDealt": 151, "totalTimeSpentDead": 210, "totalUnitsHealed": 5, "tripleKills": 0, "trueDamageDealt": 123, "trueDamageDealtToChampions": 90, "trueDamageTaken": 407, "turretKills": 0, "turretTakedowns": 1, "turretsLost": 3, "unrealKills": 0, "visionClearedPings": 0, "visionScore": 80, "visionWardsBoughtInGame": 3, "wardsKilled": 17, "wardsPlaced": 30, "win": true}], "platformId": "KR", "queueId": 420, "teams": [{"bans": [{"championId": 84, "pickTurn": 1}, {"championId": 517, "pickTurn": 2}, {"championId": 54, "pickTurn": 3}, {"championId": 53, "pickTurn": 4}, {"championId": 11, "pickTurn": 5}], "objectives": {"baron": {"first": false, "kills": 0}, "champion": {"first": true, "kills": 31}, "dragon": {"first": true, "kills": 1}, "horde": {"first": false, "kills": 0}, "inhibitor": {"first": false, "kills": 0}, "riftHerald": {"first": true, "kills": 1}, "tower": {"first": false, "kills": 3}}, "teamId": 100, "win": false}, {"bans": [{"championId": 111, "pickTurn": 6}, {"championId": 30, "pickTurn": 7}, {"championId": 517, "pickTurn": 8}, {"championId": 53, "pickTurn": 9}, {"championId": 68, "pickTurn": 10}], "objectives": {"baron": {"first": true, "kills": 1}, "champion": {"first": false, "kills": 31}, "dragon": {"first": false, "kills": 3}, "horde": {"first": false, "kills": 0}, "inhibitor": {"first": true, "kills": 2}, "riftHerald": {"first": false, "kills": 1}, "tower": {"first": true, "kills": 10}}, "teamId": 200, "win": true}], "tournamentCode": ""}}